{
 "id": 354285,
 "bug_id": 104408,
 "attachment_id": 0,
 "creation_time": "2007-05-15T09:58:13Z",
 "creator": "dfilter@FreeBSD.ORG",
 "text": "mtm         2007-05-15 08:58:05 UTC\n\n  FreeBSD src repository\n\n  Modified files:        (Branch: RELENG_6)\n    etc/rc.d             isdnd \n  Log:\n  MFC: 1.22\n  \n  date: 2007/03/30 18:36:45;  author: mtm;  state: Exp;  lines: +1 -0\n  Some rc.d commands (such as stop|restart etc.) won't automagically work\n  if we don't explicitly set the name of the executable program.\n  \n  PR: conf/104408\n  \n  Revision  Changes    Path\n  1.20.2.1  +1 -0      src/etc/rc.d/isdnd\n_______________________________________________\ncvs-all@freebsd.org mailing list\nhttp://lists.freebsd.org/mailman/listinfo/cvs-all\nTo unsubscribe, send any mail to \"cvs-all-unsubscribe@freebsd.org\""
}