{
 "id": 785217,
 "bug_id": 193433,
 "attachment_id": 0,
 "creation_time": "2014-09-08T01:55:18Z",
 "creator": "koobs@FreeBSD.org",
 "text": "lang/python just provides symlinks to relevant binaries depending on the what the default version of Python is for the system in question (DEFAULT_VERSIONS, PYTHON_DEFAULT_VERSION) \n\nRUN_DEPENDS= python:${PORTSDIR}/lang/python\n\nis likely better converted to USES=python[:\u003cversion\u003e]\n\nThe value of version of course should consider gtk20's Python version compatibility, and how the python interpreter is invoked via its scripts.\n\nSee PEP-394 for more information [1]\n\n[1] http://legacy.python.org/dev/peps/pep-0394/"
}