{
 "id": 510057,
 "bug_id": 136838,
 "attachment_id": 0,
 "creation_time": "2009-07-20T06:46:51Z",
 "creator": "dfilter@FreeBSD.ORG",
 "text": "pgollucci    2009-07-20 05:46:42 UTC\n\n  FreeBSD ports repository\n\n  Modified files:\n    www                  Makefile \n  Added files:\n    www/ruby-wgettsv     Makefile distinfo pkg-descr \n  Log:\n  Collect WWW resources and generate TSV data\n  \n  WWW:    http://alpha.mixi.co.jp/dist/tctsearch/wgettsv\n  \n  PR:             ports/136838\n  Submitted by:   Qing Feng \u003cqingfeng@me.com\u003e\n  \n  Revision  Changes    Path\n  1.2407    +1 -0      ports/www/Makefile\n  1.1       +39 -0     ports/www/ruby-wgettsv/Makefile (new)\n  1.1       +3 -0      ports/www/ruby-wgettsv/distinfo (new)\n  1.1       +3 -0      ports/www/ruby-wgettsv/pkg-descr (new)\n_______________________________________________\ncvs-all@freebsd.org mailing list\nhttp://lists.freebsd.org/mailman/listinfo/cvs-all\nTo unsubscribe, send any mail to \"cvs-all-unsubscribe@freebsd.org\""
}