{
 "id": 845622,
 "bug_id": 201267,
 "attachment_id": 0,
 "creation_time": "2015-10-24T17:56:18Z",
 "creator": "commit-hook@FreeBSD.org",
 "text": "A commit references this bug:\n\nAuthor: danfe\nDate: Sat Oct 24 17:55:24 UTC 2015\nNew revision: 400133\nURL: https://svnweb.freebsd.org/changeset/ports/400133\n\nLog:\n  - Update to version 1.1.6\n  - Define LICENSE (GPLv2)\n  - Project had moved to GitHub\n  - Clean up Makefile a bit\n\n  PR:\t201267\n\nChanges:\n  head/science/libint/Makefile\n  head/science/libint/distinfo\n  head/science/libint/files/\n  head/science/libint/files/patch-configure.in"
}