{
 "id": 821222,
 "bug_id": 199408,
 "attachment_id": 0,
 "creation_time": "2015-04-26T11:32:04Z",
 "creator": "commit-hook@FreeBSD.org",
 "text": "A commit references this bug:\n\nAuthor: jbeich\nDate: Sun Apr 26 11:31:33 UTC 2015\nNew revision: 384774\nURL: https://svnweb.freebsd.org/changeset/ports/384774\n\nLog:\n  MFH: r384747\n\n  Unbreak build on FreeBSD 8.x/9.x and DragonFly\n\n  ./PYSignal.h:35:22: error: expected namespace name\n  using namespace std::placeholders;\n                  ~~~~~^\n  ./PYSignal.h:49:18: error: no type named 'function' in namespace 'std'\n      typedef std::function\u003cR()\u003e func_type;\n              ~~~~~^\n  ./PYEditor.h:37:14: error: no type named 'shared_ptr' in namespace 'std'\n  typedef std::shared_ptr\u003cEditor\u003e EditorPtr;\n          ~~~~~^\n  PYLibPinyin.cc:223:54: error: 'getline' was not declared in this scope\n       while ((read = getline (\u0026linebuf, \u0026size, dictfile)) != -1) {\n                                                        ^\n  PR:\t\t199408\n  Reported by:\tpkg-fallout, DPorts\n  Submitted by:\tHenry Hu \u003chenry.hu.sh@gmail.com\u003e (maintainer)\n  Approved by:\tports-secteam (delphij)\n\nChanges:\n_U  branches/2015Q2/\n  branches/2015Q2/chinese/ibus-libpinyin/Makefile\n  branches/2015Q2/chinese/ibus-libpinyin/files/"
}