{
 "id": 964067,
 "bug_id": 224414,
 "attachment_id": 0,
 "creation_time": "2017-12-18T07:05:32Z",
 "creator": "paul.g.webster@googlemail.com",
 "text": "I do have some emN hardware somewhere that I know works with freebsd and my current production server seems fairly happy too:\n\nigb0: \u003cIntel(R) PRO/1000 Network Connection, Version - 2.5.3-k\u003e port 0x3000-0x30                                                                               1f mem 0xb1100000-0xb117ffff,0xb1180000-0xb1183fff irq 17 at device 0.0 on pci3\nigb0: Using MSIX interrupts with 5 vectors\nigb0: Ethernet address: 00:1e:67:c4:6f:5b\nigb0: Bound queue 0 to cpu 0\nigb0: Bound queue 1 to cpu 1\nigb0: Bound queue 2 to cpu 2\nigb0: Bound queue 3 to cpu 3\nigb0: netmap queues/slots: TX 4/10\n\n\nI BELIEVE there was a driver change for all intel network hardware coming up or just passed though, it might actually be in current (will wait for someone else to confirm) if you have the ability or time you could try installing one of the 12-snapshot ISO's to a USB pen and booting that to see if it shows the same issues."
}