{
 "id": 609997,
 "bug_id": 156930,
 "attachment_id": 0,
 "creation_time": "2011-05-10T17:20:06Z",
 "creator": "mandree@FreeBSD.org",
 "text": "Hi Dirk,\n\nnote that the current shape of netpbm frequently breaks portmaster\nupgrades, too, so we should get rid of it as soon as possible.\n\nFind below a patch to fix two major issues in graphics/netpbm:\n\n1. the addition to files/patch-Makefile.common fixes the \"compile with\nnetpbm version installed\" problem.  We\ncan remove the pre-configure check.  I've tested this with the old\n10.28 headers in /usr/local/include (taken from a package), broke before\nthe patch, no ill effects after. Basically we just make sure that\n-I$(LOCALBASE)/include comes after all the local includes.\n\nAnd certainly we don't want to wedge a PORTREVISION-bumped build...\n\nThis wasn't too hard, was it?\n\n\n2. The pre-build line makes it safe to build the whole package\n   in parallel. Consequently mark MAKE_JOBS_SAFE. Tested on a real\n   quad-core computer (AMD Phenom II X4) several times, no build\n   failures.\n\nPort maintainer (dinoex@FreeBSD.org) is cc'd.\n\nGenerated with FreeBSD Port Tools 0.99"
}