{
 "id": 74898,
 "bug_id": 24041,
 "attachment_id": 0,
 "creation_time": "2001-01-03T11:20:01Z",
 "creator": "ue@nathan.ruhr.de",
 "text": "\nThe answer to the question \"Where are the system start-up configuration\nfiles?\" gives \"/usr/local/etc.rd\" as the directory for local startup\nfiles. That should be \"/usr/local/etc/rc.d\". Patch below\n\nThe typo was found by Dirk Gouders \u003chank@musashi.et.bocholt.fh-ge.de\u003e\nduring a review of the German version of the FAQ.\n\nHow-To-Repeat: \nRead the FAQ"
}