{
 "id": 348796,
 "bug_id": 103258,
 "attachment_id": 0,
 "creation_time": "2006-09-14T12:50:17Z",
 "creator": "ino-news@spotteswoode.dnsalias.org",
 "text": "\ni have an USB card-reader.  the entry in /etc/usbd.conf is:\n\n  device \"usb cardReaderWriter\"\n    #devname \"umass0\"\n    vendor  0x058f\n    product 0x6362\n    release 0x0127\n    #attach \"/sbin/mount -v -t msdosfs -o sync /dev/da0s1 /mnt/usb-rdr\"\n    attach \"/l/sbin/mount-usb-rdr.sh\"\n    detach \"/sbin/umount -v -t msdosfs /mnt/usb-rdr\"\n\nthe script mount-usb-rdr.sh beeing the following hack:\n\n  #!/bin/sh\n  sleep 11\n  dev=\"$(find /dev/ -name 'da[01234567]s[01234567]' -print)\"\n  logger -s /sbin/mount -v -t msdosfs -o sync \"${dev:-/dev/da0s1}\" /mnt/usb-rdr\n  /sbin/mount -v -t msdosfs -o sync \"${dev:-/dev/da0s1}\" /mnt/usb-rdr\n\ni can plug it in and it works:  \"/dev/da0s1 on /mnt/usb-rdr (msdosfs,\nlocal, synchronous)\".  the detach-command doesn't work, because by the\ntime the umount(8) is executed, the USB subsystem has already\nunconfigured the device.\n\n  # umount -v /mnt/usb-rdr/\n  umount: unmount of /mnt/usb-rdr failed: Device not configured\n\nthe log shows:\n\n  \u003ckern.crit\u003e spott kernel: umass0: at uhub0 port 1 (addr 2) disconnected\n  \u003ckern.crit\u003e spott kernel: (da0:umass-sim0:0:0:0): lost device\n  \u003ckern.crit\u003e spott kernel: (da1:umass-sim0:0:0:1): lost device\n  \u003ckern.crit\u003e spott kernel: (da1:umass-sim0:0:0:1): removing device entry\n  \u003ckern.crit\u003e spott kernel: (da2:umass-sim0:0:0:2): lost device\n  \u003ckern.crit\u003e spott kernel: (da2:umass-sim0:0:0:2): removing device entry\n  \u003ckern.crit\u003e spott kernel: (da3:umass-sim0:0:0:3): lost device\n  \u003ckern.crit\u003e spott kernel: (da3:umass-sim0:0:0:3): removing device entry\n  \u003ckern.crit\u003e spott kernel: umass0: detached\n  \u003ckern.crit\u003e spott kernel: g_vfs_done():da0s1[WRITE(offset=11264, length=4096)]error = 6\n\nhowever, the device still seems to be mounted to the kernel as the\noutput of \"mount\" doesn't change. re-plugging the reader allocates a\nnew pseudo-scsi-device and messes up the the mounts: i get two msdos\nfilesystems on a single mount-point. this and a waiting period needed\nbefore actually issueing \"mount(8)\" was the reason to make an extra\nscript for mounting (see above). so i try to force-unmount:\n\n  # umount -f /mnt/usb-rdr\n\nwhich causes a kernel panic:\n\n/usr/obj/usr/src/sys/spott\n0  # kgdb kernel.debug /var/crash/vmcore.1\nkgdb: kvm_nlist(_stopped_cpus):\nkgdb: kvm_nlist(_stoppcbs):\n[GDB will not be able to debug user-mode threads: /usr/lib/libthread_db.so: Undefined symbol \"ps_pglobal_lookup\"]\nGNU gdb 6.1.1 [FreeBSD]\nCopyright 2004 Free Software Foundation, Inc.\nGDB is free software, covered by the GNU General Public License, and you are\nwelcome to change it and/or distribute copies of it under certain conditions.\nType \"show copying\" to see the conditions.\nThere is absolutely no warranty for GDB.  Type \"show warranty\" for details.\nThis GDB was configured as \"i386-marcel-freebsd\".\n\nUnread portion of the kernel message buffer:\ng_vfs_done():da0s1[READ(offset=11264, length=4096)]error = 6\n(da0:dead_sim0:0:0:0): Synchronize cache failed, status == 0x8, scsi status == 0x0\n(da0:dead_sim0:0:0:0): removing device entry\n\n\nFatal trap 12: page fault while in kernel mode\nfault virtual address   = 0x0\nfault code              = supervisor read, page not present\ninstruction pointer     = 0x20:0xc2988e0f\nstack pointer           = 0x28:0xd4eb5bf4\nframe pointer           = 0x28:0xd4eb5c44\ncode segment            = base 0x0, limit 0xfffff, type 0x1b\n                        = DPL 0, pres 1, def32 1, gran 1\nprocessor eflags        = interrupt enabled, resume, IOPL = 0\ncurrent process         = 2144 (umount)\ntrap number             = 12\npanic: page fault\nUptime: 3h11m22s\nDumping 383 MB (2 chunks)\n  chunk 0: 1MB (159 pages) ... ok\n  chunk 1: 383MB (98048 pages) 368 352 336 320 304 288 272 256 240 224 208 192 176 160 144 128 112 96 80 64 48 32 16\n\n#0  doadump () at pcpu.h:165\n165             __asm __volatile(\"movl %%fs:0,%0\" : \"=r\" (td));\n(kgdb) list *0xc2988e0f\nNo source file for address 0xc2988e0f.\n(kgdb) list *0xc2988e0f\nNo source file for address 0xc2988e0f.\n(kgdb) bt\n#0  doadump () at pcpu.h:165\n#1  0xc052d27c in boot (howto=260) at /usr/src/sys/kern/kern_shutdown.c:409\n#2  0xc052d589 in panic (fmt=0xc06b7072 \"%s\") at /usr/src/sys/kern/kern_shutdown.c:565\n#3  0xc069283c in trap_fatal (frame=0xd4eb5bb4, eva=0) at /usr/src/sys/i386/i386/trap.c:836\n#4  0xc0692512 in trap_pfault (frame=0xd4eb5bb4, usermode=0, eva=0) at /usr/src/sys/i386/i386/trap.c:744\n#5  0xc06920cf in trap (frame=\n      {tf_fs = 8, tf_es = -722796504, tf_ds = -1067188184, tf_edi = 0, tf_esi = -1030528480, tf_ebp = -722772924, tf_isp = -722773024, tf_ebx = 6, tf_edx = 0, tf_ecx = -1030150656, tf_eax = 0, tf_trapno = 12, tf_err = 0, tf_eip = -1030189553, tf_cs = 32, tf_eflags = 66178, tf_esp = -1061026112, tf_ss = -1030144000})\n    at /usr/src/sys/i386/i386/trap.c:434\n#6  0xc067dfea in calltrap () at /usr/src/sys/i386/i386/exception.s:139\n#7  0xc2988e0f in ?? ()\nPrevious frame inner to this frame (corrupt stack?)\n(kgdb) bt full\n#0  doadump () at pcpu.h:165\nNo locals.\n#1  0xc052d27c in boot (howto=260) at /usr/src/sys/kern/kern_shutdown.c:409\n        first_buf_printf = 1\n#2  0xc052d589 in panic (fmt=0xc06b7072 \"%s\") at /usr/src/sys/kern/kern_shutdown.c:565\n        td = (struct thread *) 0xc26d7000\n        bootopt = 260\n        newpanic = 0\n        ap = 0xc26d7000 \"\"\n        buf = \"page fault\", '\\0' \u003crepeats 245 times\u003e\n#3  0xc069283c in trap_fatal (frame=0xd4eb5bb4, eva=0) at /usr/src/sys/i386/i386/trap.c:836\n        code = 40\n        type = 12\n        ss = 40\n        esp = 0\n        softseg = {ssd_base = 0, ssd_limit = 1048575, ssd_type = 27, ssd_dpl = 0, ssd_p = 1, ssd_xx = 11,\n  ssd_xx1 = 1, ssd_def32 = 1, ssd_gran = 1}\n        msg = 0x0\n#4  0xc0692512 in trap_pfault (frame=0xd4eb5bb4, usermode=0, eva=0) at /usr/src/sys/i386/i386/trap.c:744\n        va = 0\n        vm = (struct vmspace *) 0x0\n        map = 0x1\n        rv = 1\n        ftype = 1 '\\001'\n        td = (struct thread *) 0xc26d7000\n        p = (struct proc *) 0xc2798000\n#5  0xc06920cf in trap (frame=\n      {tf_fs = 8, tf_es = -722796504, tf_ds = -1067188184, tf_edi = 0, tf_esi = -1030528480, tf_ebp = -722772924, tf_isp = -722773024, tf_ebx = 6, tf_edx = 0, tf_ecx = -1030150656, tf_eax = 0, tf_trapno = 12, tf_err = 0, tf_eip = -1030189553, tf_cs = 32, tf_eflags = 66178, tf_esp = -1061026112, tf_ss = -1030144000})\n    at /usr/src/sys/i386/i386/trap.c:434\n        td = (struct thread *) 0xc26d7000\n        p = (struct proc *) 0xc2798000\n        sticks = 3234083008\n        i = 0\n        ucode = 0\n        type = 12\n        code = 0\n        eva = 0\n#6  0xc067dfea in calltrap () at /usr/src/sys/i386/i386/exception.s:139\nNo locals.\n#7  0xc2988e0f in ?? ()\nNo symbol table info available.\n(kgdb) list\n139             call    trap\n140\n141             /*\n142              * Return via doreti to handle ASTs.\n143              */\n144             MEXITCOUNT\n145             jmp     doreti\n146\n147     /*\n148      * SYSCALL CALL GATE (old entry point for a.out binaries)\n(kgdb)\n\nbtw, preparing this PR and checking everything, another panic happened\nwhich i have no details for:\n\n  \u003cconsole.info\u003e spott kernel: savecore: reboot after panic: vinvalbuf: dirty bufs\n  \u003cdaemon.alert\u003e spott savecore: reboot after panic: vinvalbuf: dirty bufs\n  \u003cconsole.info\u003e spott kernel: savecore: no dump, not enough free space on device ...\n  \u003cconsole.info\u003e spott kernel: savecore: unsaved dumps found but not saved\n\nFix: \n\ni don't know how to fix this, but to work around it one must avoid the\n`-f' (force) flag to umount(8).  even without the flag, unmounting seems\nto make my system unstable.  better leave things plugged and not mess\nwith it until after shutdown and before rebooting ...  ;)\n\nregards,\n\n  clemens\nHow-To-Repeat: \ni can reproduce the panic every time by plugging in the reader,\nunplugging it and issueing:\n\n  # umount -f /mnt/usb-rdr"
}