{
 "id": 1237651,
 "bug_id": 268069,
 "attachment_id": 0,
 "creation_time": "2022-12-02T00:07:08Z",
 "creator": "fsbruva@yahoo.com",
 "text": "(In reply to ek from comment #7)\nYep, mine, too.\n\nI reverted clamav to 0.105, and successfully obtained the latest updated definitions. I just updated my copy of the ports tree, and re-built and installed clamav 1.0.0. \n\nclamd still fails to start with the new database version, with same errors. I really don't feel like bisecting the changes since 0.105..... but it might come down to that...."
}