{
 "id": 19507,
 "bug_id": 6358,
 "attachment_id": 0,
 "creation_time": "1998-05-11T00:15:54Z",
 "creator": "brett@peloton.physics.montana.edu",
 "text": "Okay, I think this is okay now.  A few notes about the new port:\n\n- the diff is relative to afterstep144 \n- all patches from patch-ab on are new patches\n- there is no scripts directory any longer\n- the penguin xpm has been removed from the files directory\n- I've marked this NO_PACKAGE - the reason is as we discussed before:\n  there are filenames w/ parentheses and spaces in them (about 130 or\n  so of them) and pkg_add just doesn't deal w/ these well at all - and I \n  didn't feel like renaming 130 files.  Maybe some sed script could fix \n  this more easily but I went w/ the NO_PACKAGE option.\n- this is no longer 1.4.4 anymore either - it's now 1.4.5.3 - I believe\n  with this latest version it's as stable as 1.0 so maybe we should \n  remove 1.4.4 from the ports tree and just replace 1.0 w/ 1.4.5.3 - I'll\n  leave that debate to the committers if they care.  If we keep a separate\n  port for these later versions can we change afterstep144 to\n  afterstep-devel (like when we had 2 gimp ports in the tree)?\n\nIn any case, here's the patch file - again it's pretty darn big.  If\nthere's troubles w/ the patches (and I don't think there are) then I've\nput a copy of my actual port for 1.4.5.3 at:\n\n\thttp://peloton.physics.montana.edu/brett/afterstep-devel.tar.gz\n\nBrett\n\n*********************************************************\nBrett Taylor \t\tbrett@peloton.physics.montana.edu\nhttp://peloton.physics.montana.edu/brett/\n\n\n***********************************************************************\n\ndiff -ruN afterstep144/Makefile afterstep-devel/Makefile\n--- afterstep144/Makefile\tSun Apr 19 22:38:55 1998\n+++ afterstep-devel/Makefile\tSun May 10 17:01:44 1998\n@@ -1,52 +1,71 @@\n-# New ports collection makefile for:\tafterstep\n-# Version required:\t1.0\n-# Date created:\t\tOctober 29th 1996\n-# Whom:\t\t\tjfitz@FreeBSD.ORG\n+# New ports collection makefile for:\tafterstep-1.4.4\n+# Version required:\t1.4.4\n+# Date created:\t\t1 May 1998\n+# Whom:\t\t\tBrett Taylor\n #\n-# $Id: Makefile,v 1.19 1998/04/20 04:38:55 asami Exp $\n+# $Id:$\n #\n \n-DISTNAME=\tAfterStep-1.0\n-PKGNAME=\tafterstep-1.0\n-CATEGORIES=\tx11\n-MASTER_SITES=\tftp://afterstep.foo.net/pub/AfterStep/\n+DISTNAME=\tAfterStep-1.4.5.0\n+PKGNAME=\tafterstep-1.4.5.3\n+CATEGORIES=     x11\n+MASTER_SITES=   ftp://ftp.afterstep.org/pub/\n+EXTRACT_SUFX=   .tgz\n \n-MAINTAINER=\tjfitz@FreeBSD.ORG\n+PATCH_SITES=    ftp://ftp.afterstep.org/pub/\n+PATCHFILES=\tAfterStep1450-to-1451.patch.gz AfterStep1451-to-1453.patch.gz\n \n-LIB_DEPENDS=\tXpm\\\\.4\\\\.:${PORTSDIR}/graphics/xpm\n+MAINTAINER=\tbrett@peloton.physics.montana.edu\n \n-BROKEN=\t\trepository copy from 1.0, awaiting upgrade to 1.44\n+LIB_DEPENDS=    Xpm\\\\.4\\\\.:${PORTSDIR}/graphics/xpm\n \n-USE_X11=\tyes\n+PATCH_DIST_STRIP=\t-p1\n+NO_PACKAGE=\tyes\n+#there are 130 files or so with spaces or parens in their name which \n+#makes pkg_add die so we can't easily package this\n+\n+WRKSRC=         ${WRKDIR}/AfterStep\n+\n+IS_INTERACTIVE=\tyes\n+USE_IMAKE=\tyes\n INSTALL_TARGET=\tinstall install.man\n MANCOMPRESSED=\tyes\n-MAN1=\t\tafterstep.1 asclock.1 Animate.1 Audio.1 Auto.1 Banner.1 Pager.1 Wharf.1\n+\n+HAS_CONFIGURE=\tyes\n+\n+XMKMF= \txmkmf\n+pre-configure:\n+\t@${ECHO_MSG} \"The interactive portion is asking you about languages\"\n+\t@${ECHO_MSG} \"and color use by asclock.\"\n+pre-patch:\n+\t@${ECHO_MSG} \"*******************************************************\"\n+\t@${ECHO_MSG} \"The source will be patched to use xv to put non-pixmaps\"\n+\t@${ECHO_MSG} \"on the root window using a tiled format.  If you would\"\n+\t@${ECHO_MSG} \"prefer a different viewer or the image not to be tiled,\"\n+\t@${ECHO_MSG} \"please stop the build now and edit patch-aa to your\"\n+\t@${ECHO_MSG} \"preferred configuration.\"\n+\t@${ECHO_MSG} \"*******************************************************\"\n \n pre-build:\n-\t\t@ cd ${WRKSRC}; sh MakeMakefiles\n+\t@ cd ${WRKSRC}; ${MAKE} Makefiles\n \n-post-install:\t\n-\t\t@ ${MKDIR} -p ${PREFIX}/lib/X11/afterstep/backgrounds/\n-\t\t${INSTALL_DATA} ${WRKSRC}/backgrounds/* ${PREFIX}/lib/X11/afterstep/backgrounds/\n-\t\t@ ${MKDIR} -p ${PREFIX}/lib/X11/afterstep/sounds/\n-\t\t${INSTALL_DATA} ${WRKSRC}/sounds/* ${PREFIX}/lib/X11/afterstep/sounds/\n-\t\t@ ${MKDIR} -p ${PREFIX}/include/X11/pixmaps/\n-.if defined(USE_HICOLOR_ICONS)\n-\t\t${INSTALL_DATA} ${WRKSRC}/icons/*.xpm ${PREFIX}/include/X11/pixmaps/\n-.else\n-.if !defined(BATCH)\n-\t\t@echo \"===\u003e  Note: to use the hi-color icons,\"\n-\t\t@echo \"      reinstall this port with -DUSE_HICOLOR_ICONS\"\n-\t\t@echo \"      defined\"\n-.endif\n-\t\t@for file in AFstep.xpm penguin.xpm monitor_bsd.xpm; do \\\n-\t\t\t${CP} ${FILESDIR}/$$file ${WRKSRC}/icons/8bit; \\\n-\t\tdone\n-\t\t${INSTALL_DATA} ${WRKSRC}/icons/8bit/*.xpm ${PREFIX}/include/X11/pixmaps/\n-.endif\n-\t\t@ ${MKDIR} -p ${PREFIX}/lib/X11/afterstep/doc/\n-\t\t@for file in CHANGES CREDITS README README.8bit INSTALL FAQ module-interface.txt; do \\\n-\t\t\t${INSTALL_DATA} ${WRKSRC}/$$file ${PREFIX}/lib/X11/afterstep/doc/; \\\n-\t\tdone\n+#there's a missing man file for ASSound - touch so we can install without\n+#removing the ASSound module and breaking something else\n+pre-install:\n+\t@${TOUCH} ${WRKSRC}/modules/ASSound/ASSound.man\n+\n+post-install:\n+\t${INSTALL_SCRIPT} ${WRKSRC}/afterdoc/afterstepdoc ${PREFIX}/bin/\n+\t${INSTALL_DATA} ${FILESDIR}/monitor_bsd.xpm ${PREFIX}/include/X11/pixmaps/\n+\t@${RM} ${PREFIX}/share/afterstep/*.orig\n+\t@${RM} ${PREFIX}/share/afterstep/feels/*.orig\n+\t@${RM} ${PREFIX}/share/afterstep/looks/*.orig\n+\t@${RM} ${PREFIX}/share/afterstep/non-configurable/desk*/*.orig\n+\t@${RM} ${PREFIX}/share/afterstep/non-configurable/tmp/*.orig\n+\t@${RM} ${PREFIX}/share/afterstep/desktop/icons/*/*.orig\n+\t@${RM} ${PREFIX}/share/afterstep/desktop/buttons/*.orig\n+\t@${ECHO_MSG} \"********************************************************\"\n+\t@${ECHO_MSG} \"HTML docs are included in ${PREFIX}/share/doc/afterstep\"\n+\t@${ECHO_MSG} \"********************************************************\"\n \n .include \u003cbsd.port.mk\u003e\ndiff -ruN afterstep144/files/AFstep.xpm afterstep-devel/files/AFstep.xpm\n--- afterstep144/files/AFstep.xpm\tSat Mar 29 23:04:57 1997\n+++ afterstep-devel/files/AFstep.xpm\tWed Dec 31 17:00:00 1969\n@@ -1,72 +0,0 @@\n-/* XPM */\n-static char *noname[] = {\n-/* width height ncolors chars_per_pixel */\n-\"48 47 18 1\",\n-/* colors */\n-\"` c #858678\",\n-\"a c #B2C0DC\",\n-\"b c #3D4C41\",\n-\"c c #14E314\",\n-\"d c #E3DF2A\",\n-\"e c #4E5151\",\n-\"f c #3F3D3F\",\n-\"g c #101214\",\n-\"h c #686560\",\n-\"i c #020102\",\n-\"j c #2F3538\",\n-\"k c #A30E1C\",\n-\"l c #7D6F73\",\n-\"m c #00018D\",\n-\"n c #545851\",\n-\"o c #A19685\",\n-\"p c #356E3B\",\n-\"q c #242134\",\n-/* pixels */\n-\"aaaaaaaaaaaaaaaaaaaaaaaaaaaaaaaaaaaaaaaaaaaaaaaa\",\n-\"aaaaaaaaaaaaaaaaaaaaaaaaa`aaaaaaaaaaaaaaaaaaaaaa\",\n-\"aaaaaaaaaaaaaaaaaaaaaaaa``aaaaaaaaaaaaaaaaaaaaaa\",\n-\"aaaaaaaaaaaaaaaaaaaaakkkkig``aaaaaaaaaaaaaaaaaaa\",\n-\"aaaaaaaaaaaaaaaaaaa`kkggqfqiqo`aaaaaaaaaaaaaaaaa\",\n-\"aaaaaaaaaaaaaaaaaooqgkkgkkbfgifo`aaaaaaaaaaaaaaa\",\n-\"aaaaaaaaaaaaaaa``qggikkkkkjbffqgbaaaaaaaaaaaaaaa\",\n-\"aaaaaaaaaaaaaaoqiqfgikkkkkfjbnejqqn`aaaaaaaaaaaa\",\n-\"aaaaaaaaaao`lggqeeebkkkkkkkkqjgjbfiboaaaaaaaaaaa\",\n-\"aaaaaaaaaahdpbqgqqjebbpbkkkkkkkkbegoaaaaaaaaaaaa\",\n-\"aaaaaaaaagiddddddbqqqjfbpfkkkkkkpeg`aaaaaaaaaaaa\",\n-\"aaaaaoafiiidbjhdddddpbqqqqgkkknpefq`aaaaaaaaaaaa\",\n-\"aaaoofiqfqgddqjgjdddddddhdpkkppeeqn`aaaaaaaaaaaa\",\n-\"`ooeggjebqgpdggpdddjppddddhfpbeebqoaaaaaaaaaaaaa\",\n-\"abgqjbbfbqgqdpddd`ejjjdddhebnneeejeaaaaaaaaaaaaa\",\n-\"oibeefefefggddddnjjegpd`ejeenefenfjfl`aaaaaaaaaa\",\n-\"aiqnebbfneqgbdhmjjbhenhjeneeeenbgqa`eqaaaaaaaaaa\",\n-\"`gijebffnnqqjdegbeeeenneeeebfnejlhooejqhaaaaaaaa\",\n-\"o`iijnefenqqgddddefnenhnefeenhifa`afjnngqaaaaaaa\",\n-\"aoiiijhnfnbggddddfnenneeebnehqioaa`afjnhegn`aaaa\",\n-\"a`iigiqnefggpdd`jeheennenhebcccphla```qjffqfaoaa\",\n-\"a`figiiqnnjqpdhjehnnneenhjpccccccoooa`aehleege`a\",\n-\"aaoigggijhhbeejnhnnenenhjgcgigccphn`oa``alnhgh`a\",\n-\"aa`iigggiqenehnnhnneehhnqccqgccchjccolaahehbg`aa\",\n-\"aa`giggggifhhnehejmpnnnbqpcpccphljccjhaenhnih`aa\",\n-\"aa`higgggiqlneenbmmnjmmhqgcccblleqccfllnhbgiaaaa\",\n-\"aaaoiigggiqhnnnejimmmmm`fipcccccccccehh`fgin`aaa\",\n-\"aaaoeigggighebnejimmmmn`lfggcccccccph`ljgiioaaaa\",\n-\"aaaaofiggginnnhegmmqmmmhhhnpggpcpgghllqgiioaaaaa\",\n-\"aaaaa`jigginnnnqgmmimmmmhh`hpppppghohqgigaaaaaaa\",\n-\"aaaaaa`qigiflhhhbmejqmmmmhpfm`nnh``hqgiq`aaaaaaa\",\n-\"aaaaaaa`giiijhhhhhhbqgmmmmjmmhhl`lfqgij`aaaaaaaa\",\n-\"aaaaaaaaaiiiifhhhnhhnqgmmmmmm`lhleqgif`aaaaaaaaa\",\n-\"aaaaaaaaaaiiiijl`hhlhnjgmmmmh`lhbqginoaaaaaaaaaa\",\n-\"aaaaaaaaaaoiiiiflhnhh`hfqmgjh`hfqgih`aaaaaaaaaaa\",\n-\"aaaaaaaaaaaoiiiiflhhhlhhhhnh`hqqgilaaaaaaaaaaaaa\",\n-\"aaaaaaaaaaaaoiigieohnhnhhhllnqggi`aaaaaaaaaaaaaa\",\n-\"aaaaaaaaaaaaa`iiiiflhnnhll`ngqgi`aaaaaaaaaaaaaaa\",\n-\"aaaaaaaaaaaaaaliigieohnnh`ngqgioaaaaaaaaaaaaaaaa\",\n-\"aaaaaaaaaaaaaaahiiiinoh``ngqigoaaaaaaaaaaaaaaaaa\",\n-\"aaaaaaaaaaaaaaaonigiib`hfggig`aaaaaaaaaaaaaaaaaa\",\n-\"aaaaaaaaaaaaaaaaobigiiffqgij`aaaaaaaaaaaaaaaaaaa\",\n-\"aaaaaaaaaaaaaaaaa`jigigjgif`aaaaaaaaaaaaaaaaaaaa\",\n-\"aaaaaaaaaaaaaaaaaa`gigqqin`aaaaaaaaaaaaaaaaaaaaa\",\n-\"aaaaaaaaaaaaaaaaaaa`iiiin`aaaaaaaaaaaaaaaaaaaaaa\",\n-\"aaaaaaaaaaaaaaaaaaaa`iihaaaaaaaaaaaaaaaaaaaaaaaa\",\n-\"aaaaaaaaaaaaaaaaaaaa`oo`aaaaaaaaaaaaaaaaaaaaaaaa\"\n-};\ndiff -ruN afterstep144/files/md5 afterstep-devel/files/md5\n--- afterstep144/files/md5\tSat May 17 13:48:20 1997\n+++ afterstep-devel/files/md5\tFri May  1 15:30:48 1998\n@@ -1 +1,3 @@\n-MD5 (AfterStep-1.0.tar.gz) = 2c56247e1914e25a455df3c8d03b0663\n+MD5 (AfterStep-1.4.5.0.tgz) = bdc506d37472252875b900222a4b55f7\n+MD5 (AfterStep1450-to-1451.patch.gz) = 99a007c6e811ae5292e64e0854899211\n+MD5 (AfterStep1451-to-1453.patch.gz) = eb97c9cfb57a1c106dc9a0d0993de66e\ndiff -ruN afterstep144/files/penguin.xpm afterstep-devel/files/penguin.xpm\n--- afterstep144/files/penguin.xpm\tSat Mar 29 23:05:01 1997\n+++ afterstep-devel/files/penguin.xpm\tWed Dec 31 17:00:00 1969\n@@ -1,73 +0,0 @@\n-/* XPM */\n-static char *noname[] = {\n-/* width height ncolors chars_per_pixel */\n-\"48 48 18 1\",\n-/* colors */\n-\"` c #000000\",\n-\"a c #F3BD14\",\n-\"b c #828796\",\n-\"c c #B2C0DC\",\n-\"d c #221C1D\",\n-\"e c #160011\",\n-\"f c #685A5E\",\n-\"g c #A0A3AC\",\n-\"h c #F6F6F3\",\n-\"i c #6E727E\",\n-\"j c #040304\",\n-\"k c #FCFCF7\",\n-\"l c #A28359\",\n-\"m c #DFCF80\",\n-\"n c #E3EDF1\",\n-\"o c #FFFFFF\",\n-\"p c #E1B11E\",\n-\"q c #EEEEED\",\n-/* pixels */\n-\"cccccccccccccccccccccccjjjjjjjjccccccccccccccccc\",\n-\"ccnooooooooooooooooooojjjjjjjffjoooooooooooooodc\",\n-\"cnqqqnqqqnqqqnqqqnqqqjjjjjjjjjfdjqqqqqnqhhhhhidc\",\n-\"conqnhnqnhnqnhnqnhnqjjjjjejjjjjjjjnnqnhnhhhhhidc\",\n-\"coqnqqqnqqqnqqqnqqqnjjjjjjjjjjjjjjqqnqqqhhhhgidc\",\n-\"conhnqnhnqnhnqnhnqnhjjjdjjjjjjjjjjjnhnqnnhhggidc\",\n-\"coqqqn``````````````jdgidjjigcfdjjj``````fgggidc\",\n-\"conqnh`iiiiiiiibibbbjhnhhjdqhhgjjjjbbbbbiobggidc\",\n-\"coqnqq`iiiiiiibbbbbbjcjdhddhjbhdjjjff`diioggcidc\",\n-\"conhnq`iiiibbbbbgbggjcjdfdehjbnfjjjf`dffiogcgidc\",\n-\"coqqqn`iiibbbbbbggggjdflaaaajihjjjjeeddfiocggidc\",\n-\"conqnh`iibbbggggggggjjpaaaaaappjjjj`ddffiogcgidc\",\n-\"coqnqq`ibbbbbgggggggjlpaaaaaappejjjddfffiocggidc\",\n-\"conhnq`ibbbgggbggbggjdpaaaaalppjjdjffffiiogggidc\",\n-\"coqqqn`ibbbgggbggbggdifpaalpppmdjjfjffiiiogggidc\",\n-\"conqnh`bbbggggggggggdbclpppgmcncjjjjdiiiiogggidc\",\n-\"coqnqq`ibbbgggbggbggjbncllgcchhhdjjjjiiiiogggidc\",\n-\"conhnq`bbbgggggggggdjqhccccnhhhhqjjejjiiiogggiec\",\n-\"coqqqn`ibbbbggbbgbdjghkhcchhhhhhkjjjjjiiiogggfdc\",\n-\"conqnh`ibbgbgggbgbjdhhhhhhhhkhhhhgjjjjjiiogggiec\",\n-\"coqnqq`ibbbbbgbgcjjbhhhkkhkkhhhhhqjjjjjjiogggfdc\",\n-\"conhnq`iibbbbbggjjjgcqhhnnhhhccccndjjjjjdogggiec\",\n-\"coqqqn`iiibbbbbbjjdckhhhqhhhkhhncchjdjjjjogggfec\",\n-\"conqnh`iiibbbbbjjjghhkqhhhhhhhhhkncjjjjjjjggbfec\",\n-\"coqnqq`iiiiibbbjdjhhhkkkhhhhkhhkhknnjjjjjjgggfec\",\n-\"conhnq`iiiiiibijjbhhhhkhhhkkhhhhhkhhdjjjjjbgbfjc\",\n-\"coqqqn`iiiiiiijdjhhhhkhqhkhhhkhhkhkhdjjjjjjbbfec\",\n-\"conqnn`iiiiiiijjfhhhhhhnkhkhhhhhhhhhfjjjjjjgbfjc\",\n-\"coqnqn`iiiiiijjjchhkhkhnhhhhhhkhhhhhbjjjjjjbbfec\",\n-\"connnn`iiiiiijdjqhhhkhhnhhhhhhkkhhhhgjjjjjjjbf`c\",\n-\"coqnnn`iiiiijjdjqhhhhkhnhhhhkhhkhhkhcjjjjjjjbfec\",\n-\"connnn`iiiiijjdjnhhkhhhnkhhhhhhhhhhhnjjjjjjjbf`c\",\n-\"connnngooooojpfdhkhhhkhnhhhhhhhhhhhhbdjjjjjjbf`c\",\n-\"connnnncncccpaalfhkhkhhnhhhhhhhhhhmpljjjjjjbbf`c\",\n-\"connncnccccmpaaafdhhhhknhhhhhhhhhhpapjjjjjpabf`c\",\n-\"connncccccmppaaaaejqhhhhhhhkhhhhhhpapejjjfaaif`c\",\n-\"cogiiiiilpppaaaaapjjnhkhkhhhhhkhhcpaplddlpaaff`c\",\n-\"ci`````ppaaaaaaaaadjjfqhhhhhkhhhhclppppppaaaa``c\",\n-\"cccccccaaaaaaaaaaapejjqhhhhhhhhhkclpppppaaaaaacc\",\n-\"cccccccpaaaaaaaaaaaljjqkhhhhhhkhhglpaaaaaaaaaapc\",\n-\"cccccccpaaaaaaaaaaaamhhhhkhhhhhhgjlpaaaaaaaaaaaa\",\n-\"cccccccpaaaaaaaaaaaapqhhkkhhhhhdjelpaaaaaaaaaaac\",\n-\"cccccccpaaaaaaaaaaaapfhhhkhhhbjjjelpaaaaaaaaaacc\",\n-\"cccccccpppaaaaaaaaaapljjjjjjjjjjjdppaaaaaaapcccc\",\n-\"ccccccclpppppppaaaappfejjjjjjjjjjdlpaaaapplccccc\",\n-\"ccccccci```lllpppppplfejj```````jdfppppplccccccc\",\n-\"ccccccccccccccffllllffccccccccccccdlplplcccccccc\",\n-\"cccccccccccccccccdfdfccccccccccccccdffdccccccccc\"\n-};\ndiff -ruN afterstep144/patches/patch-aa afterstep-devel/patches/patch-aa\n--- afterstep144/patches/patch-aa\tSun Mar 23 09:22:48 1997\n+++ afterstep-devel/patches/patch-aa\tSun May 10 11:50:48 1998\n@@ -1,51 +1,36 @@\n-*** configure.h.orig\tSun Mar  2 11:50:40 1997\n---- configure.h\tThu Mar 20 21:31:42 1997\n+*** configure.h\tSun May 10 11:49:16 1998\n+--- configure.h\tSun May 10 11:49:59 1998\n ***************\n-*** 1,6 ****\n-! #define AFTERDIR     \"/usr/lib/X11/afterstep\"\n-! #define AFTER_ICONDIR   \"/usr/include/X11/bitmaps:/usr/include/X11/pixmaps\"\n-! #define STEPRC         \"/usr/lib/X11/afterstep/system.steprc\"\n-  \n-  /* If you would like gradients, uncomment this */\n-  #define ENABLE_TEXTURE\n---- 1,6 ----\n-! #define AFTERDIR     \"%%PREFIX%%/lib/X11/afterstep\"\n-! #define AFTER_ICONDIR   \"%%PREFIX%%/include/X11/bitmaps:%%PREFIX%%/include/X11/pixmaps\"\n-! #define STEPRC         \"%%PREFIX%%/lib/X11/afterstep/system.steprc\"\n+*** 16,22 ****\n   \n-  /* If you would like gradients, uncomment this */\n-  #define ENABLE_TEXTURE\n-***************\n-*** 17,23 ****\n-   * Imake wants to leave binaries, then choose the second line here.\n-   * If you want to install it in a different directory, uncomment and\n-   * edit the first line */\n-! #define AFTER_BIN_DIR BINDIR=/usr/bin/X11\n-  \n-  /* Compiler over-ride for Imakefiles */\n-  /* Leave it as shown to get your default compiler */\n---- 17,23 ----\n-   * Imake wants to leave binaries, then choose the second line here.\n-   * If you want to install it in a different directory, uncomment and\n-   * edit the first line */\n-! #define AFTER_BIN_DIR BINDIR=%%PREFIX%%/bin\n+  #define AFTER_BPMDIR\t\"/usr/X11R6/include/X11/bitmaps\"\n+  #define AFTER_XPMDIR\t\"/usr/X11R6/include/X11/pixmaps\"\n+! #define AFTER_SHAREDIR\t\"/usr/share/afterstep\"\n+  \n+  /* Home directories NEEDED */\n+  \n+--- 16,22 ----\n+  \n+  #define AFTER_BPMDIR\t\"/usr/X11R6/include/X11/bitmaps\"\n+  #define AFTER_XPMDIR\t\"/usr/X11R6/include/X11/pixmaps\"\n+! #define AFTER_SHAREDIR\t\"/usr/X11R6/share/afterstep\"\n+  \n+  /* Home directories NEEDED */\n   \n-  /* Compiler over-ride for Imakefiles */\n-  /* Leave it as shown to get your default compiler */\n ***************\n-*** 59,65 ****\n+*** 55,61 ****\n    ***************************************************************************/\n-  #define XPM                      \n-  /*  linker flags needed to locate and link in the Xpm library, if you use it */\n-! #define XPMLIBRARY -L/usr/lib/X11 -lXpm\n+  \n+  /* #define XIMAGELOADER  \"xli -onroot -quiet -colors 20\" */\n+! #define XIMAGELOADER  \"xv -root -quit\"       /* you can add \"-rmode 5\" */\n   \n   /***************************************************************************\n-   *#define M4\n---- 59,65 ----\n+   * #define ANIM*\n+--- 55,61 ----\n    ***************************************************************************/\n-  #define XPM                      \n-  /*  linker flags needed to locate and link in the Xpm library, if you use it */\n-! #define XPMLIBRARY -L%%PREFIX%%/lib -lXpm\n+  \n+  /* #define XIMAGELOADER  \"xli -onroot -quiet -colors 20\" */\n+! #define XIMAGELOADER  \"xv -root -rmode 0 -quit\"       \n   \n   /***************************************************************************\n-   *#define M4\n+   * #define ANIM*\ndiff -ruN afterstep144/patches/patch-ab afterstep-devel/patches/patch-ab\n--- afterstep144/patches/patch-ab\tSun Mar 23 09:22:49 1997\n+++ afterstep-devel/patches/patch-ab\tSun May 10 11:57:12 1998\n@@ -1,112 +1,19 @@\n-*** sample.steprc.orig\tSun Mar  9 06:30:22 1997\n---- sample.steprc\tThu Mar 20 21:37:46 1997\n+*** afterstep/wharf\tSun Mar 29 03:14:48 1998\n+--- afterstep/wharf\tFri May  1 15:07:11 1998\n ***************\n-*** 166,176 ****\n-  # ModulePath is a colon-separated list, just like a regular unix PATH\n-  # Any Module must be found within the path in order to be located\n-  # and executed\n-! ModulePath          /usr/lib/X11/afterstep:/usr/X11R6/lib/X11/afterstep\n-  # Another colon-separated list pointing to your pixmaps (color icons)\n-! PixmapPath          /usr/include/X11/pixmaps/\n-  # Path for your ugly black\u0026white icons\n-! IconPath            /usr/include/X11/bitmaps/\n-  \n-  # Various styles which can be associated with specific applications\n-  # Sticky -- remains \"stuck\" on all desks\n---- 166,176 ----\n-  # ModulePath is a colon-separated list, just like a regular unix PATH\n-  # Any Module must be found within the path in order to be located\n-  # and executed\n-! ModulePath          %%PREFIX%%/lib/X11/afterstep\n-  # Another colon-separated list pointing to your pixmaps (color icons)\n-! PixmapPath          %%PREFIX%%/include/X11/pixmaps/\n-  # Path for your ugly black\u0026white icons\n-! IconPath            %%PREFIX%%/include/X11/bitmaps/\n-  \n-  # Various styles which can be associated with specific applications\n-  # Sticky -- remains \"stuck\" on all desks\n-***************\n-*** 290,296 ****\n-          # Place the green carpet image onto the background upon startup\n-          # I personally recommend xli/xloadimage, but xv seems to be\n-          # ubiquitous in the unix world so I'll use that \n-! \t# Exec\t\"I\"\texec xv -root -quit /usr/lib/X11/afterstep/backgrounds/carpet.green.jpg\n-  \tExec\t\"I\"\texec xsetroot -solid DarkGrey\n-  EndFunction\n-  \n---- 290,296 ----\n-          # Place the green carpet image onto the background upon startup\n-          # I personally recommend xli/xloadimage, but xv seems to be\n-          # ubiquitous in the unix world so I'll use that \n-! \t# Exec\t\"I\"\texec xv -root -quit %%PREFIX%%/lib/X11/afterstep/backgrounds/carpet.green.jpg\n-  \tExec\t\"I\"\texec xsetroot -solid DarkGrey\n-  EndFunction\n-  \n-***************\n-*** 465,485 ****\n-  # Images ... quick way to view the included default background images\n-  Popup \"Images\"\n-  \tTitle\t\"Images\"\n-! \tExec\t\"Brick\"\t\texec xv -root -quit /usr/lib/X11/afterstep/backgrounds/brick.jpg\n-! \tExec\t\"Coins\"\t\texec xv -root -quit /usr/lib/X11/afterstep/backgrounds/coins.jpg\n-! \tExec\t\"Dark Wood\"\texec xv -root -quit /usr/lib/X11/afterstep/backgrounds/darkwood.jpg\n-! \tExec\t\"Eyes\"\t\texec xv -root -quit /usr/lib/X11/afterstep/backgrounds/eyes.jpg\n-! \tExec\t\"Glass\"\t\texec xv -root -quit /usr/lib/X11/afterstep/backgrounds/glass.jpg\n-! \tExec\t\"Green Carpet\"\texec xv -root -quit /usr/lib/X11/afterstep/backgrounds/carpet.green.jpg\n-! \tExec\t\"Parquet\"\texec xv -root -quit /usr/lib/X11/afterstep/backgrounds/parquet.jpg\n-! \tExec\t\"Pebbles\"\texec xv -root -quit /usr/lib/X11/afterstep/backgrounds/pebbles.jpg\n-! \tExec\t\"Rock\"\t\texec xv -root -quit /usr/lib/X11/afterstep/backgrounds/rock.tile.jpg\n-! \tExec\t\"Rope\"\t\texec xv -root -quit /usr/lib/X11/afterstep/backgrounds/rope.weave.jpg\n-! \tExec\t\"Stucco\"\texec xv -root -quit /usr/lib/X11/afterstep/backgrounds/stucco.jpg\n-! \tExec\t\"Tile\"\t\texec xv -root -quit /usr/lib/X11/afterstep/backgrounds/tile.check.jpg\n-! \tExec\t\"Tree Bark\"\texec xv -root -quit /usr/lib/X11/afterstep/backgrounds/bark.jpg\n-! \tExec\t\"Volcanic\"\texec xv -root -quit /usr/lib/X11/afterstep/backgrounds/volcanic.jpg\n-! \tExec\t\"Wood\"\t\texec xv -root -quit /usr/lib/X11/afterstep/backgrounds/wood.jpg\n-  EndPopup\n-  \n-  # Background settings ... choose from either Solid Colors or Color Images\n---- 465,485 ----\n-  # Images ... quick way to view the included default background images\n-  Popup \"Images\"\n-  \tTitle\t\"Images\"\n-! \tExec\t\"Brick\"\t\texec xv -root -quit %%PREFIX%%/lib/X11/afterstep/backgrounds/brick.jpg\n-! \tExec\t\"Coins\"\t\texec xv -root -quit %%PREFIX%%/lib/X11/afterstep/backgrounds/coins.jpg\n-! \tExec\t\"Dark Wood\"\texec xv -root -quit %%PREFIX%%/lib/X11/afterstep/backgrounds/darkwood.jpg\n-! \tExec\t\"Eyes\"\t\texec xv -root -quit %%PREFIX%%/lib/X11/afterstep/backgrounds/eyes.jpg\n-! \tExec\t\"Glass\"\t\texec xv -root -quit %%PREFIX%%/lib/X11/afterstep/backgrounds/glass.jpg\n-! \tExec\t\"Green Carpet\"\texec xv -root -quit %%PREFIX%%/lib/X11/afterstep/backgrounds/carpet.green.jpg\n-! \tExec\t\"Parquet\"\texec xv -root -quit %%PREFIX%%/lib/X11/afterstep/backgrounds/parquet.jpg\n-! \tExec\t\"Pebbles\"\texec xv -root -quit %%PREFIX%%/lib/X11/afterstep/backgrounds/pebbles.jpg\n-! \tExec\t\"Rock\"\t\texec xv -root -quit %%PREFIX%%/lib/X11/afterstep/backgrounds/rock.tile.jpg\n-! \tExec\t\"Rope\"\t\texec xv -root -quit %%PREFIX%%/lib/X11/afterstep/backgrounds/rope.weave.jpg\n-! \tExec\t\"Stucco\"\texec xv -root -quit %%PREFIX%%/lib/X11/afterstep/backgrounds/stucco.jpg\n-! \tExec\t\"Tile\"\t\texec xv -root -quit %%PREFIX%%/lib/X11/afterstep/backgrounds/tile.check.jpg\n-! \tExec\t\"Tree Bark\"\texec xv -root -quit %%PREFIX%%/lib/X11/afterstep/backgrounds/bark.jpg\n-! \tExec\t\"Volcanic\"\texec xv -root -quit %%PREFIX%%/lib/X11/afterstep/backgrounds/volcanic.jpg\n-! \tExec\t\"Wood\"\t\texec xv -root -quit %%PREFIX%%/lib/X11/afterstep/backgrounds/wood.jpg\n-  EndPopup\n-  \n-  # Background settings ... choose from either Solid Colors or Color Images\n-***************\n-*** 605,614 ****\n-  Module Audio    \n-  \n-  # Select your normal audio player\n-! #*AudioPlayCmd /usr/bin/showaudio\n-  \n-  # Select the directory containing your sounds\n-! #*AudioDir /home/frank/mac/sounds\n-  \n-  #*AudioDelay 1\n-  \n---- 605,614 ----\n-  Module Audio    \n-  \n-  # Select your normal audio player\n-! #*AudioPlayCmd /usr/local/bin/showaudio\n-  \n-  # Select the directory containing your sounds\n-! #*AudioDir %%PREFIX%%/lib/X11/afterstep/sounds\n-  \n-  #*AudioDelay 1\n-  \n+*** 105,111 ****\n+   #\n+   # Xiterminal\n+   #\n+!  *Wharf xiterm linux-penguin.xpm Exec \"-\" xiterm -sl 500 -vb \u0026\n+   # Screen saver\n+   #\n+   *Wharf xlock Recycler.xpm  Exec \"-\" xlock -nolock -nice 0 -mode random \u0026\n+--- 105,111 ----\n+   #\n+   # Xiterminal\n+   #\n+!  *Wharf xiterm monitor_bsd.xpm Exec \"-\" xiterm -sl 500 -vb \u0026\n+   # Screen saver\n+   #\n+   *Wharf xlock Recycler.xpm  Exec \"-\" xlock -nolock -nice 0 -mode random \u0026\ndiff -ruN afterstep144/patches/patch-ac afterstep-devel/patches/patch-ac\n--- afterstep144/patches/patch-ac\tWed Dec 31 17:00:00 1969\n+++ afterstep-devel/patches/patch-ac\tSun May 10 14:31:47 1998\n@@ -0,0 +1,40 @@\n+*** afterdoc/afterstepdoc\tSun May 10 14:27:38 1998\n+--- afterdoc/afterstepdoc\tSun May 10 14:29:07 1998\n+***************\n+*** 4,28 ****\n+  # First try standard path, then local, then other possible paths\n+  #\n+  \n+! if [ -x /usr/X11R6/bin/netscape ]\n+! then\n+!   /usr/X11R6/bin/netscape /usr/share/afterstep/doc/afterstep.html\n+! elif [ -x /usr/local/bin/netscape ]\n+    then\n+!    /usr/local/bin/netscape /usr/share/afterstep/doc/afterstep.html\n+! elif [ -x /usr/local/netscape/netscape ]\n+!   then\n+!   /usr/local/netscape/netscape /usr/share/afterstep/doc/afterstep.html\n+! elif [ -x /opt/netscape/netscape ]\n+!   then\n+!   /opt/netscape/netscape /usr/share/afterstep/doc/afterstep.html\n+! elif [ -x /usr/bin/lynx ]\n+!   then\n+!   xiterm -bg black -fg peachpuff -sl 500 -vb -e \"/usr/bin/lynx /usr/share/afterstep/doc/afterstep.html\"\n+  elif [ -x /usr/local/bin/lynx ]\n+    then\n+!   xiterm -bg black -fg peachpuff -sl 500 -vb -e \"/usr/local/bin/lynx /usr/share/afterstep/doc/afterstep.html\"\n+! elif [ -x /bin/lynx ]\n+!   then\n+!   xiterm -bg black -fg peachpuff -sl 500 -vb -e \"/bin/lynx /usr/share/afterstep/doc/afterstep.html\"\n+  fi\n+--- 4,13 ----\n+  # First try standard path, then local, then other possible paths\n+  #\n+  \n+! if [ -x /usr/local/bin/netscape ]\n+    then\n+!    /usr/local/bin/netscape /usr/X11R6/share/doc/afterstep/afterstep.html\n+  elif [ -x /usr/local/bin/lynx ]\n+    then\n+!   xiterm -bg black -fg peachpuff -sl 500 -vb -e \"/usr/local/bin/lynx /usr/X11R6/share/doc/afterstep/afterstep.html\"\n+  fi\ndiff -ruN afterstep144/patches/patch-ad afterstep-devel/patches/patch-ad\n--- afterstep144/patches/patch-ad\tWed Dec 31 17:00:00 1969\n+++ afterstep-devel/patches/patch-ad\tSun May 10 14:32:37 1998\n@@ -0,0 +1,39 @@\n+*** afterdoc/Imakefile.bak\tSun May 10 14:29:18 1998\n+--- afterdoc/Imakefile\tSun May 10 14:30:46 1998\n+***************\n+*** 5,24 ****\n+  AFTER_BIN_DIR\n+  AFTER_MAN_DIR\n+  \n+! InstallNonExecFile(afterstep.html,/usr/share/afterstep/doc)\n+! InstallNonExecFile(afterstep-1.html,/usr/share/afterstep/doc)\n+! InstallNonExecFile(afterstep-2.html,/usr/share/afterstep/doc)\n+! InstallNonExecFile(afterstep-3.html,/usr/share/afterstep/doc)\n+! InstallNonExecFile(afterstep-4.html,/usr/share/afterstep/doc)\n+! InstallNonExecFile(afterstep-5.html,/usr/share/afterstep/doc)\n+! InstallNonExecFile(afterstep-6.html,/usr/share/afterstep/doc)\n+! InstallNonExecFile(afterstep-7.html,/usr/share/afterstep/doc)\n+! InstallNonExecFile(afterstep-8.html,/usr/share/afterstep/doc)\n+! InstallNonExecFile(afterstep-9.html,/usr/share/afterstep/doc)\n+! InstallTarget(install,afterstepdoc,-m 0755,$(BINDIR))\n+  \n+- afterstep.html::\n+- \tsgml2html afterstep.sgml\n+- \n+- all::\n+- \techo \"You must have sgmltools \u0026 run 'make html' to make afterdoc\"\n+--- 5,18 ----\n+  AFTER_BIN_DIR\n+  AFTER_MAN_DIR\n+  \n+! InstallNonExecFile(afterstep.html,/usr/X11R6/share/doc/afterstep)\n+! InstallNonExecFile(afterstep-1.html,/usr/X11R6/share/doc/afterstep)\n+! InstallNonExecFile(afterstep-2.html,/usr/X11R6/share/doc/afterstep)\n+! InstallNonExecFile(afterstep-3.html,/usr/X11R6/share/doc/afterstep)\n+! InstallNonExecFile(afterstep-4.html,/usr/X11R6/share/doc/afterstep)\n+! InstallNonExecFile(afterstep-5.html,/usr/X11R6/share/doc/afterstep)\n+! InstallNonExecFile(afterstep-6.html,/usr/X11R6/share/doc/afterstep)\n+! InstallNonExecFile(afterstep-7.html,/usr/X11R6/share/doc/afterstep)\n+! InstallNonExecFile(afterstep-8.html,/usr/X11R6/share/doc/afterstep)\n+! InstallNonExecFile(afterstep-9.html,/usr/X11R6/share/doc/afterstep)\n+  \ndiff -ruN afterstep144/patches/patch-ae afterstep-devel/patches/patch-ae\n--- afterstep144/patches/patch-ae\tWed Dec 31 17:00:00 1969\n+++ afterstep-devel/patches/patch-ae\tSun May 10 11:57:34 1998\n@@ -0,0 +1,40 @@\n+*** Imakefile\tSun May 10 11:54:54 1998\n+--- Imakefile\tSun May 10 11:55:46 1998\n+***************\n+*** 17,28 ****\n+  \tafterdoc \\\n+  \tapps/ascd \\\n+  \tapps/asclock \\\n+- \tapps/asfsm \\\n+- \tapps/asload \\\n+  \tapps/asmail \\\n+- \tapps/asmix \\\n+- \tapps/asmixer \\\n+- \tapps/asprint \\\n+  \tapps/xiterm/src \\\n+  \tmodules/ASSound \\\n+  \tmodules/Animate \\\n+--- 17,23 ----\n+***************\n+*** 43,52 ****\n+  MakeSubdirs($(SUBDIRS))\n+  \n+  install::\n+! \tif [ -d /usr/share/afterstep/ ] ; \\\n+! \tthen mv /usr/share/afterstep/ /usr/share/oldafterstep ; \\\n+  \tfi\n+! \tcp -R afterstep /usr/share/afterstep\n+  \n+  mrproper::\n+  \trm -fr config.cache config.log config.status Makefile.bak *.orig\n+--- 38,47 ----\n+  MakeSubdirs($(SUBDIRS))\n+  \n+  install::\n+! \tif [ -d /usr/X11R6/share/afterstep/ ] ; \\\n+! \tthen mv /usr/X11R6/share/afterstep/ /usr/X11R6/share/oldafterstep ; \\\n+  \tfi\n+! \tcp -R afterstep /usr/X11R6/share/afterstep\n+  \n+  mrproper::\n+  \trm -fr config.cache config.log config.status Makefile.bak *.orig\ndiff -ruN afterstep144/patches/patch-af afterstep-devel/patches/patch-af\n--- afterstep144/patches/patch-af\tWed Dec 31 17:00:00 1969\n+++ afterstep-devel/patches/patch-af\tSun May 10 12:02:55 1998\n@@ -0,0 +1,12 @@\n+*** modules/Form/Form.c\tFri Apr 17 23:07:30 1998\n+--- modules/Form/Form.c\tFri Apr 17 23:07:49 1998\n+***************\n+*** 31,37 ****\n+  #include \u003cX11/cursorfont.h\u003e\n+  #define XK_MISCELLANY\n+  #include \u003cX11/keysymdef.h\u003e\n+- #include \u003cmalloc.h\u003e\n+  #include \u003cstring.h\u003e\n+  #include \u003csys/types.h\u003e\n+  #include \u003csys/time.h\u003e\n+--- 31,36 ----\ndiff -ruN afterstep144/patches/patch-ag afterstep-devel/patches/patch-ag\n--- afterstep144/patches/patch-ag\tWed Dec 31 17:00:00 1969\n+++ afterstep-devel/patches/patch-ag\tSun May 10 13:42:53 1998\n@@ -0,0 +1,19 @@\n+*** afterstep/base.8bpp\tSun May 10 13:39:35 1998\n+--- afterstep/base.8bpp\tSun May 10 13:40:00 1998\n+***************\n+*** 9,15 ****\n+  #\n+  ModulePath\t\t/usr/X11R6/bin/\n+  IconPath\t\t/usr/X11R6/include/X11/bitmaps/\n+! PixmapPath\t\t/usr/X11R6/include/X11/pixmaps/:~/GNUstep/Library/AfterStep/desktop/buttons/:/usr/share/afterstep/desktop/buttons/:~/GNUstep/Library/AfterStep/desktop/icons/8bpp/:/usr/share/afterstep/desktop/icons/8bpp/:~/GNUstep/Library/AfterStep/desktop /\nicons/common/:/usr/share/afterstep/desktop/icons/common/:~/GNUstep/Library/AfterStep/desktop/backgrounds/:/usr/share/afterstep/desktop/backgrounds/\n+  #\n+  ##########################################################################\n+  \n+--- 9,15 ----\n+  #\n+  ModulePath\t\t/usr/X11R6/bin/\n+  IconPath\t\t/usr/X11R6/include/X11/bitmaps/\n+! PixmapPath\t\t/usr/X11R6/include/X11/pixmaps/:~/GNUstep/Library/AfterStep/desktop/buttons/:/usr/X11R6/share/afterstep/desktop/buttons/:~/GNUstep/Library/AfterStep/desktop/icons/8bpp/:/usr/X11R6/share/afterstep/desktop/icons/8bpp/:~/GNUstep/Library/After S\ntep/desktop/icons/common/:/usr/X11R6/share/afterstep/desktop/icons/common/:~/GNUstep/Library/AfterStep/desktop/backgrounds/:/usr/X11R6/share/afterstep/desktop/backgrounds/\n+  #\n+  ##########################################################################\n+  \ndiff -ruN afterstep144/patches/patch-ah afterstep-devel/patches/patch-ah\n--- afterstep144/patches/patch-ah\tWed Dec 31 17:00:00 1969\n+++ afterstep-devel/patches/patch-ah\tSun May 10 13:43:03 1998\n@@ -0,0 +1,19 @@\n+*** afterstep/base.16bpp \tSun May 10 13:26:42 1998\n+--- afterstep/base.16bpp\tSun May 10 13:38:11 1998\n+***************\n+*** 9,15 ****\n+  #\n+  ModulePath\t\t/usr/X11R6/bin/\n+  IconPath\t\t/usr/X11R6/include/X11/bitmaps/\n+! PixmapPath\t\t/usr/X11R6/include/X11/pixmaps/:~/GNUstep/Library/AfterStep/desktop/buttons/:/usr/share/afterstep/desktop/buttons/:~/GNUstep/Library/AfterStep/desktop/icons/16bpp/:/usr/share/afterstep/desktop/icons/16bpp/:~/GNUstep/Library/AfterStep/deskt o\np/icons/common/:/usr/share/afterstep/desktop/icons/common/:~/GNUstep/Library/AfterStep/desktop/backgrounds/:/usr/share/afterstep/desktop/backgrounds/\n+  #\n+  ##########################################################################\n+  \n+--- 9,15 ----\n+  #\n+  ModulePath\t\t/usr/X11R6/bin/\n+  IconPath\t\t/usr/X11R6/include/X11/bitmaps/\n+! PixmapPath\t\t/usr/X11R6/include/X11/pixmaps/:~/GNUstep/Library/AfterStep/desktop/buttons/:/usr/X11R6/share/afterstep/desktop/buttons/:~/GNUstep/Library/AfterStep/desktop/icons/16bpp/:/usr/X11R6/share/afterstep/desktop/icons/16bpp/:~/GNUstep/Library/Aft e\nrStep/desktop/icons/common/:/usr/X11R6/share/afterstep/desktop/icons/common/:~/GNUstep/Library/AfterStep/desktop/backgrounds/:/usr/X11R6/share/afterstep/desktop/backgrounds/\n+  #\n+  ##########################################################################\n+  \ndiff -ruN afterstep144/patches/patch-ai afterstep-devel/patches/patch-ai\n--- afterstep144/patches/patch-ai\tWed Dec 31 17:00:00 1969\n+++ afterstep-devel/patches/patch-ai\tSun May 10 13:43:11 1998\n@@ -0,0 +1,19 @@\n+*** afterstep/base.24bpp\tSun May 10 13:38:42 1998\n+--- afterstep/base.24bpp\tSun May 10 13:39:26 1998\n+***************\n+*** 9,15 ****\n+  #\n+  ModulePath\t\t/usr/X11R6/bin/\n+  IconPath\t\t/usr/X11R6/include/X11/bitmaps/\n+! PixmapPath\t\t/usr/X11R6/include/X11/pixmaps/:~/GNUstep/Library/AfterStep/desktop/buttons/:/usr/share/afterstep/desktop/buttons/:~/GNUstep/Library/AfterStep/desktop/icons/16bpp/:/usr/share/afterstep/desktop/icons/16bpp/:~/GNUstep/Library/AfterStep/deskt o\np/icons/common/:/usr/share/afterstep/desktop/icons/common/:~/GNUstep/Library/AfterStep/desktop/backgrounds/:/usr/share/afterstep/desktop/backgrounds/\n+  #\n+  ##########################################################################\n+  \n+--- 9,15 ----\n+  #\n+  ModulePath\t\t/usr/X11R6/bin/\n+  IconPath\t\t/usr/X11R6/include/X11/bitmaps/\n+! PixmapPath\t\t/usr/X11R6/include/X11/pixmaps/:~/GNUstep/Library/AfterStep/desktop/buttons/:/usr/X11R6/share/afterstep/desktop/buttons/:~/GNUstep/Library/AfterStep/desktop/icons/16bpp/:/usr/X11R6/share/afterstep/desktop/icons/16bpp/:~/GNUstep/Library/Aft e\nrStep/desktop/icons/common/:/usr/X11R6/share/afterstep/desktop/icons/common/:~/GNUstep/Library/AfterStep/desktop/backgrounds/:/usr/X11R6/share/afterstep/desktop/backgrounds/\n+  #\n+  ##########################################################################\n+  \ndiff -ruN afterstep144/patches/patch-aj afterstep-devel/patches/patch-aj\n--- afterstep144/patches/patch-aj\tWed Dec 31 17:00:00 1969\n+++ afterstep-devel/patches/patch-aj\tSun May 10 14:54:21 1998\n@@ -0,0 +1,19 @@\n+*** afterstep/database\tSun May 10 14:53:19 1998\n+--- afterstep/database\tSun May 10 14:53:43 1998\n+***************\n+*** 13,19 ****\n+  Style   \"*clock\"        StaysOnTop, WindowListSkip, NoHandles\n+  Style   \"ghostview\"     Icon text.xpm\n+  Style   \"gimp\"          Icon 3dpaint.xpm\n+! Style   \"*term\"         Icon linux-penguin.xpm\n+  Style   \"Untitled*\"     Icon AfterStep3.xpm\n+  Style   \"xcalc\"         Icon xcalc.xpm\n+  Style   \"xli\"           Icon monalisa.xpm\n+--- 13,19 ----\n+  Style   \"*clock\"        StaysOnTop, WindowListSkip, NoHandles\n+  Style   \"ghostview\"     Icon text.xpm\n+  Style   \"gimp\"          Icon 3dpaint.xpm\n+! Style   \"*term\"         Icon monitor_bsd.xpm\n+  Style   \"Untitled*\"     Icon AfterStep3.xpm\n+  Style   \"xcalc\"         Icon xcalc.xpm\n+  Style   \"xli\"           Icon monalisa.xpm\ndiff -ruN afterstep144/patches/patch-ak afterstep-devel/patches/patch-ak\n--- afterstep144/patches/patch-ak\tWed Dec 31 17:00:00 1969\n+++ afterstep-devel/patches/patch-ak\tSun May 10 16:19:12 1998\n@@ -0,0 +1,46 @@\n+*** modules/PagerNOXPM/Imakefile\tSun May 10 16:18:34 1998\n+--- modules/PagerNOXPM/Imakefile\tSun May 10 16:17:44 1998\n+***************\n+*** 1,6 ****\n+  #include \u003c../../configure.h\u003e\n+  \n+! #ifndef XPM\n+  \n+  /* OVERRIDE_COMPILER */\n+  \n+--- 1,6 ----\n+  #include \u003c../../configure.h\u003e\n+  \n+! #ifdef XPM\n+  \n+  /* OVERRIDE_COMPILER */\n+  \n+***************\n+*** 15,27 ****\n+  \n+  LINTLIBS = $(LINTXLIB)\n+  \n+! ComplexProgramTarget(Pager)\n+  \n+  /* LinkFile would be nicer */\n+  install::\n+! \tln -sf $(BINDIR)/Pager $(BINDIR)/WPager\n+! \tln -sf $(BINDIR)/Pager $(BINDIR)/XPager\n+! \tln -sf $(BINDIR)/Pager $(BINDIR)/YPager\n+! \tln -sf $(BINDIR)/Pager $(BINDIR)/ZPager\n+   \n+  #endif\n+--- 15,27 ----\n+  \n+  LINTLIBS = $(LINTXLIB)\n+  \n+! ComplexProgramTarget(Pager-noxpm)\n+  \n+  /* LinkFile would be nicer */\n+  install::\n+! \tln -sf $(BINDIR)/Pager-noxpm $(BINDIR)/WPager-noxpm\n+! \tln -sf $(BINDIR)/Pager-noxpm $(BINDIR)/XPager-noxpm\n+! \tln -sf $(BINDIR)/Pager-noxpm $(BINDIR)/YPager-noxpm\n+! \tln -sf $(BINDIR)/Pager-noxpm $(BINDIR)/ZPager-noxpm\n+   \n+  #endif\ndiff -ruN afterstep144/pkg/COMMENT afterstep-devel/pkg/COMMENT\n--- afterstep144/pkg/COMMENT\tTue Jul 23 01:36:32 1996\n+++ afterstep-devel/pkg/COMMENT\tSun May 10 12:43:05 1998\n@@ -1 +1 @@\n-This window manager is a continuation of the Bowman NeXTSTEP clone.\n+This is AfterStep-1.4.5.3 a development version of the AfterStep.\ndiff -ruN afterstep144/pkg/DESCR afterstep-devel/pkg/DESCR\n--- afterstep144/pkg/DESCR\tTue Jul 23 01:36:32 1996\n+++ afterstep-devel/pkg/DESCR\tSun May 10 12:42:55 1998\n@@ -1,21 +1,10 @@\n-AfterStep is a continuation of the BowMan window manager which was\n-originally put together by Bo Yang. BowMan was based on the fvwm window\n-manager, written by Robert Nation. Fvwm was based on code from twm. And so\n-on... It is designed to emulate some of the look and feel of the NEXTSTEP®\n-user interface, while adding useful, requested, and neat features. The\n-changes which comprise AfterStep's personality were originally part of\n-BowMan development, but due to a desire to move past simple emulation and\n-into a niche as its own valuable window manager, the current designers\n-decided to change the project name and move on. BowMan development may\n-continue, but we will no longer be a part of it.\n-\n-Major changes from fvwm are:\n-\n-- NEXTSTEP-like title bar, title buttons, borders and corners. BowMan's\n-  Wharf is a much worked-out version of GoodStuff.  To avoid copyright\n-  complications it is not called a \"dock.\" \n-- NEXTSTEP style menu. However, the menus are not controlled by\n-  applications; they are more of pop-up service lists on the root window.\n-- NEXTSTEP style icons. These styles are hard-coded in the program, which is\n-  good for the consistent look of the NEXTSTEP interface.\n+This is a development version of AfterStep-1.4.5.3.  AfterStep is a NeXTStep\n+style window manager and features quick easy configuration of the look and\n+feel of your setup without the use of a .steprc file.  Configuration in \n+most cases is far easier than it used to be.  There are a few small bugs, \n+but this release is fairly stable.  Included are a number of AfterStep \n+applications including asclock, ascd, and xiterm.  There are a number of\n+other very Linux specific applications which are not at present included.\n \n+Brett Taylor\n+brett@peloton.physics.montana.edu\ndiff -ruN afterstep144/pkg/PLIST afterstep-devel/pkg/PLIST\n--- afterstep144/pkg/PLIST\tSun Jul 13 11:27:12 1997\n+++ afterstep-devel/pkg/PLIST\tSun May 10 16:46:37 1998\n@@ -1,66 +1,649 @@\n+bin/ascd\n bin/afterstep\n bin/asclock\n-lib/X11/afterstep/Animate\n-lib/X11/afterstep/Audio\n-lib/X11/afterstep/Auto\n-lib/X11/afterstep/Banner\n-lib/X11/afterstep/Pager\n-lib/X11/afterstep/Wharf\n-lib/X11/afterstep/system.steprc\n-lib/X11/afterstep/backgrounds/bark.jpg\n-lib/X11/afterstep/backgrounds/brick.jpg\n-lib/X11/afterstep/backgrounds/carpet.green.jpg\n-lib/X11/afterstep/backgrounds/coins.jpg\n-lib/X11/afterstep/backgrounds/darkwood.jpg\n-lib/X11/afterstep/backgrounds/eyes.jpg\n-lib/X11/afterstep/backgrounds/glass.jpg\n-lib/X11/afterstep/backgrounds/parquet.jpg\n-lib/X11/afterstep/backgrounds/pebbles.jpg\n-lib/X11/afterstep/backgrounds/rock.tile.jpg\n-lib/X11/afterstep/backgrounds/rope.weave.jpg\n-lib/X11/afterstep/backgrounds/stucco.jpg\n-lib/X11/afterstep/backgrounds/tile.check.jpg\n-lib/X11/afterstep/backgrounds/volcanic.jpg\n-lib/X11/afterstep/backgrounds/wood.jpg\n-lib/X11/afterstep/doc/CHANGES\n-lib/X11/afterstep/doc/CREDITS\n-lib/X11/afterstep/doc/README\n-lib/X11/afterstep/doc/README.8bit\n-lib/X11/afterstep/doc/FAQ\n-lib/X11/afterstep/doc/INSTALL\n-lib/X11/afterstep/doc/module-interface.txt\n-lib/X11/afterstep/sounds/bong.au\n-lib/X11/afterstep/sounds/clink.au\n-lib/X11/afterstep/sounds/cowbell.au\n-lib/X11/afterstep/sounds/crash.au\n-lib/X11/afterstep/sounds/drip.au\n-lib/X11/afterstep/sounds/gong.au\n-lib/X11/afterstep/sounds/meepmeep.au\n-lib/X11/afterstep/sounds/small-step.au\n-lib/X11/afterstep/sounds/train.au\n+bin/asmail\n+bin/xiterm\n+bin/ASSound\n+bin/Animate\n+bin/Audio\n+bin/Auto\n+bin/Banner\n+bin/Clean\n+bin/Form\n+bin/Ident\n+bin/Save\n+bin/Scroll\n+bin/Pager\n+bin/WPager\n+bin/XPager\n+bin/YPager\n+bin/ZPager\n+bin/Pager-noxpm\n+bin/WPager-noxpm\n+bin/XPager-noxpm\n+bin/YPager-noxpm\n+bin/ZPager-noxpm\n+bin/Wharf\n+bin/WinList\n+bin/Zharf\n+bin/afterstepdoc\n include/X11/pixmaps/monitor_bsd.xpm\n-include/X11/pixmaps/3dpaint.xpm\n-include/X11/pixmaps/AFstep.xpm\n-include/X11/pixmaps/FileFolders.xpm\n-include/X11/pixmaps/KeysOnChain.xpm\n-include/X11/pixmaps/YellowBlueRedGeometry.xpm\n-include/X11/pixmaps/interface.xpm\n-include/X11/pixmaps/monalisa.xpm\n-include/X11/pixmaps/monitor.xpm\n-include/X11/pixmaps/netscape3.xpm\n-include/X11/pixmaps/penguin.xpm\n-include/X11/pixmaps/shutdown.xpm\n-include/X11/pixmaps/text.xpm\n-include/X11/pixmaps/writeletter.xpm\n-man/man1/afterstep.1.gz\n-man/man1/asclock.1.gz\n-man/man1/Animate.1.gz\n+man/man1/ascd.1.gz\n man/man1/Audio.1.gz\n man/man1/Auto.1.gz\n+man/man1/asclock.1.gz\n+man/man1/asmail.1.gz\n+man/man1/xiterm.1.gz\n+man/man1/Clean.1.gz\n+man/man1/ASSound.1.gz\n+man/man1/Animate.1.gz\n man/man1/Banner.1.gz\n+man/man1/Form.1.gz\n+man/man1/Ident.1.gz\n+man/man1/Save.1.gz\n man/man1/Pager.1.gz\n+man/man1/Pager-noxpm.1.gz\n+man/man1/Scroll.1.gz\n man/man1/Wharf.1.gz\n-@dirrm lib/X11/afterstep/doc\n-@dirrm lib/X11/afterstep/backgrounds\n-@dirrm lib/X11/afterstep/sounds\n-@dirrm lib/X11/afterstep\n+man/man1/Zharf.1.gz\n+man/man1/WinList.1.gz\n+man/man1/afterstep.1.gz\n+share/afterstep/looks/look.Wouter\n+share/afterstep/looks/look.Nextish\n+share/afterstep/looks/look.Black\n+share/afterstep/looks/look.purenext\n+share/afterstep/looks/look.DEFAULT\n+share/afterstep/looks/look.redish\n+share/afterstep/looks/look.red\n+share/afterstep/looks/look.Neptho\n+share/afterstep/looks/look.Dark\n+share/afterstep/looks/look.orchid\n+share/afterstep/looks/look.turquoise\n+share/afterstep/looks/look.lightgrey\n+share/afterstep/looks/look.lightblue\n+share/afterstep/looks/look.greyblue\n+share/afterstep/looks/look.DeepBlue\n+share/afterstep/looks/look.Stone\n+share/afterstep/looks/look.nogradient\n+share/afterstep/looks/look.James\n+share/afterstep/looks/look.AfterStep\n+share/afterstep/looks/look.NewFeatures\n+share/afterstep/looks/look.Guylhem\n+share/afterstep/non-configurable/desk1/look.16bpp\n+share/afterstep/non-configurable/desk1/look.8bpp\n+share/afterstep/non-configurable/desk1/background\n+share/afterstep/non-configurable/desk1/feel.16bpp\n+share/afterstep/non-configurable/desk1/feel.24bpp\n+share/afterstep/non-configurable/desk1/look.24bpp\n+share/afterstep/non-configurable/desk1/feel.8bpp\n+share/afterstep/non-configurable/desk0/feel.8bpp\n+share/afterstep/non-configurable/desk0/look.8bpp\n+share/afterstep/non-configurable/desk0/look.16bpp\n+share/afterstep/non-configurable/desk0/background\n+share/afterstep/non-configurable/desk0/feel.24bpp\n+share/afterstep/non-configurable/desk0/look.24bpp\n+share/afterstep/non-configurable/desk0/feel.16bpp\n+share/afterstep/non-configurable/desk3/feel.8bpp\n+share/afterstep/non-configurable/desk3/look.8bpp\n+share/afterstep/non-configurable/desk3/look.16bpp\n+share/afterstep/non-configurable/desk3/background\n+share/afterstep/non-configurable/desk3/feel.24bpp\n+share/afterstep/non-configurable/desk3/look.24bpp\n+share/afterstep/non-configurable/desk3/feel.16bpp\n+share/afterstep/non-configurable/desk2/feel.16bpp\n+share/afterstep/non-configurable/desk2/look.8bpp\n+share/afterstep/non-configurable/desk2/feel.8bpp\n+share/afterstep/non-configurable/desk2/background\n+share/afterstep/non-configurable/desk2/feel.24bpp\n+share/afterstep/non-configurable/desk2/look.24bpp\n+share/afterstep/non-configurable/desk2/look.16bpp\n+share/afterstep/non-configurable/tmp/startmenu\n+share/afterstep/non-configurable/Make8bitXPMs\n+share/afterstep/non-configurable/Xpm2Jpg\n+share/afterstep/start/Quit/Exit ?\n+share/afterstep/start/Quit/Close this session\n+share/afterstep/start/Quit/Restart this session\n+share/afterstep/start/Quit/Restart with twm\n+share/afterstep/start/Quit/Restart with wmaker\n+share/afterstep/start/Quit/ReRead configuration\n+share/afterstep/start/Modules/- XLock with ...\n+share/afterstep/start/Modules/Ident\n+share/afterstep/start/Modules/Clean\n+share/afterstep/start/Modules/Banner\n+share/afterstep/start/Modules/Audio\n+share/afterstep/start/Modules/Zharf\n+share/afterstep/start/Modules/WinList\n+share/afterstep/start/Modules/Pager\n+share/afterstep/start/Modules/- Help about ...\n+share/afterstep/start/Modules/Animate\n+share/afterstep/start/Modules/Auto\n+share/afterstep/start/Modules/Wharf\n+share/afterstep/start/Modules/- Find a file ...\n+share/afterstep/start/Modules/Scroll\n+share/afterstep/start/Modules/- Quit ...\n+share/afterstep/start/Modules/- Run a command ...\n+share/afterstep/start/Modules/- Take screenshot ...\n+share/afterstep/start/Modules/- Take windowshot ...\n+share/afterstep/start/Modules/- FTP to ...\n+share/afterstep/start/Screen savers/Without password/Stop animation\n+share/afterstep/start/Screen savers/Without password/Forest\n+share/afterstep/start/Screen savers/Without password/Laser\n+share/afterstep/start/Screen savers/Without password/Mountain\n+share/afterstep/start/Screen savers/Without password/Qix\n+share/afterstep/start/Screen savers/Without password/Shape\n+share/afterstep/start/Screen savers/Without password/Spermatozoid\n+share/afterstep/start/Screen savers/Without password/Spline\n+share/afterstep/start/Screen savers/Without password/Star Trek\n+share/afterstep/start/Screen savers/Without password/Firework\n+share/afterstep/start/Screen savers/With password/Star Trek\n+share/afterstep/start/Screen savers/With password/Forest\n+share/afterstep/start/Screen savers/With password/Laser\n+share/afterstep/start/Screen savers/With password/Mountain\n+share/afterstep/start/Screen savers/With password/Qix\n+share/afterstep/start/Screen savers/With password/Shape\n+share/afterstep/start/Screen savers/With password/Spermatozoid\n+share/afterstep/start/Screen savers/With password/Spline\n+share/afterstep/start/Screen savers/With password/Firework\n+share/afterstep/start/Applications/Office/Invest\n+share/afterstep/start/Applications/Office/Ps viewer\n+share/afterstep/start/Applications/Office/XEmacs\n+share/afterstep/start/Applications/Office/Lyx\n+share/afterstep/start/Applications/Office/HP 48\n+share/afterstep/start/Applications/Office/XEphemeride\n+share/afterstep/start/Applications/Office/Dvi viewer\n+share/afterstep/start/Applications/Office/File manager\n+share/afterstep/start/Applications/Office/Plot\n+share/afterstep/start/Applications/Office/Finance\n+share/afterstep/start/Applications/Office/RPN calculator\n+share/afterstep/start/Applications/Games/Asteroids\n+share/afterstep/start/Applications/Games/X Eyes\n+share/afterstep/start/Applications/Games/Tetris\n+share/afterstep/start/Applications/Games/Patience\n+share/afterstep/start/Applications/Games/X Boing\n+share/afterstep/start/Applications/Games/Invaders\n+share/afterstep/start/Applications/Games/Galaga\n+share/afterstep/start/Applications/Games/Block Out\n+share/afterstep/start/Applications/KDE/KDE-Games/Minehunt\n+share/afterstep/start/Applications/KDE/KDE-Games/Patience\n+share/afterstep/start/Applications/KDE/KDE-Games/Tetris\n+share/afterstep/start/Applications/KDE/Calculator\n+share/afterstep/start/Applications/KDE/Display manager\n+share/afterstep/start/Applications/KDE/Help\n+share/afterstep/start/Applications/KDE/Find a file\n+share/afterstep/start/Applications/KDE/Editor\n+share/afterstep/start/Applications/KDE/View picture\n+share/afterstep/start/Applications/KDE/File manager\n+share/afterstep/start/Applications/KDE/Font manager\n+share/afterstep/start/Applications/KDE/Screen lock\n+share/afterstep/start/Applications/KDE/Paintbrush\n+share/afterstep/start/Applications/KDE/Command prompt\n+share/afterstep/start/Applications/KDE/Editor (hex)\n+share/afterstep/start/Applications/Accessories/Color name\n+share/afterstep/start/Applications/Accessories/Colors\n+share/afterstep/start/Applications/Accessories/X logo\n+share/afterstep/start/Applications/Accessories/Help\n+share/afterstep/start/Applications/Accessories/Notepad\n+share/afterstep/start/Applications/Accessories/Clock\n+share/afterstep/start/Applications/Accessories/Calculator\n+share/afterstep/start/Applications/Accessories/System load\n+share/afterstep/start/Applications/Accessories/Screen magnify\n+share/afterstep/start/Applications/Accessories/Battery\n+share/afterstep/start/Applications/Accessories/Keyboard leds\n+share/afterstep/start/Applications/Accessories/Change defaults\n+share/afterstep/start/Applications/Accessories/Change keyboard\n+share/afterstep/start/Applications/Accessories/Change screen\n+share/afterstep/start/Applications/Accessories/X pirate logo\n+share/afterstep/start/Applications/Accessories/System charge\n+share/afterstep/start/Applications/Accessories/Grab screen\n+share/afterstep/start/Applications/Accessories/Reset color map\n+share/afterstep/start/Applications/Accessories/Color map\n+share/afterstep/start/Applications/Accessories/Window infos\n+share/afterstep/start/Applications/StEP applications/Volume\n+share/afterstep/start/Applications/StEP applications/System load\n+share/afterstep/start/Applications/StEP applications/File system\n+share/afterstep/start/Applications/StEP applications/Sound mixer\n+share/afterstep/start/Applications/StEP applications/Mail checker\n+share/afterstep/start/Applications/StEP applications/Modem checker\n+share/afterstep/start/Applications/StEP applications/Printer\n+share/afterstep/start/Applications/StEP applications/PPP checker\n+share/afterstep/start/Applications/StEP applications/Radio Tuner\n+share/afterstep/start/Applications/StEP applications/Trash\n+share/afterstep/start/Applications/StEP applications/CD player\n+share/afterstep/start/Applications/StEP applications/File manager\n+share/afterstep/start/Applications/StEP applications/Clock\n+share/afterstep/start/Applications/Network/Connect to internet\n+share/afterstep/start/Applications/Network/Netscape\n+share/afterstep/start/Applications/Network/Lynx\n+share/afterstep/start/Applications/Network/Mail\n+share/afterstep/start/Applications/Network/Ftp\n+share/afterstep/start/Applications/Network/Telnet\n+share/afterstep/start/Applications/Network/Irc\n+share/afterstep/start/Applications/Network/Connect to a BBS\n+share/afterstep/start/Applications/Network/X ftp\n+share/afterstep/start/Applications/Network/News\n+share/afterstep/start/Applications/Network/Connect by ppp\n+share/afterstep/start/Applications/Medias/CD Player\n+share/afterstep/start/Applications/Medias/Modules\n+share/afterstep/start/Applications/Medias/Midi\n+share/afterstep/start/Applications/Medias/Pictures\n+share/afterstep/start/Applications/Medias/Mixer\n+share/afterstep/start/Applications/Medias/MPEG-3\n+share/afterstep/start/Applications/Medias/The gimp\n+share/afterstep/start/Decorations/Animations/Spermatozoid\n+share/afterstep/start/Decorations/Animations/Qix\n+share/afterstep/start/Decorations/Animations/Star Trek\n+share/afterstep/start/Decorations/Animations/Laser\n+share/afterstep/start/Decorations/Animations/Spline\n+share/afterstep/start/Decorations/Animations/Mountain\n+share/afterstep/start/Decorations/Animations/Shape\n+share/afterstep/start/Decorations/Animations/Firework\n+share/afterstep/start/Decorations/Animations/Forest\n+share/afterstep/start/Decorations/Cursors/xterm\n+share/afterstep/start/Decorations/Cursors/num_glyphs\n+share/afterstep/start/Decorations/Cursors/arrow\n+share/afterstep/start/Decorations/Cursors/based_arrow_down\n+share/afterstep/start/Decorations/Cursors/based_arrow_up\n+share/afterstep/start/Decorations/Cursors/boat\n+share/afterstep/start/Decorations/Cursors/bogosity\n+share/afterstep/start/Decorations/Cursors/bottom_left_corner\n+share/afterstep/start/Decorations/Cursors/bottom_right_corner\n+share/afterstep/start/Decorations/Cursors/bottom_side\n+share/afterstep/start/Decorations/Cursors/bottom_tee\n+share/afterstep/start/Decorations/Cursors/box_spiral\n+share/afterstep/start/Decorations/Cursors/center_ptr\n+share/afterstep/start/Decorations/Cursors/circle\n+share/afterstep/start/Decorations/Cursors/clock\n+share/afterstep/start/Decorations/Cursors/coffee_mug\n+share/afterstep/start/Decorations/Cursors/cross\n+share/afterstep/start/Decorations/Cursors/cross_reverse\n+share/afterstep/start/Decorations/Cursors/crosshair\n+share/afterstep/start/Decorations/Cursors/diamond_cross\n+share/afterstep/start/Decorations/Cursors/dot\n+share/afterstep/start/Decorations/Cursors/dotbox\n+share/afterstep/start/Decorations/Cursors/double_arrow\n+share/afterstep/start/Decorations/Cursors/draft_large\n+share/afterstep/start/Decorations/Cursors/draft_small\n+share/afterstep/start/Decorations/Cursors/draped_box\n+share/afterstep/start/Decorations/Cursors/exchange\n+share/afterstep/start/Decorations/Cursors/fleur\n+share/afterstep/start/Decorations/Cursors/gobbler\n+share/afterstep/start/Decorations/Cursors/gumby\n+share/afterstep/start/Decorations/Cursors/hand1\n+share/afterstep/start/Decorations/Cursors/hand2\n+share/afterstep/start/Decorations/Cursors/heart\n+share/afterstep/start/Decorations/Cursors/icon\n+share/afterstep/start/Decorations/Cursors/iron_cross\n+share/afterstep/start/Decorations/Cursors/left_ptr\n+share/afterstep/start/Decorations/Cursors/left_side\n+share/afterstep/start/Decorations/Cursors/left_tee\n+share/afterstep/start/Decorations/Cursors/leftbutton\n+share/afterstep/start/Decorations/Cursors/ll_angle\n+share/afterstep/start/Decorations/Cursors/lr_angle\n+share/afterstep/start/Decorations/Cursors/man\n+share/afterstep/start/Decorations/Cursors/middlebutton\n+share/afterstep/start/Decorations/Cursors/mouse\n+share/afterstep/start/Decorations/Cursors/pencil\n+share/afterstep/start/Decorations/Cursors/pirate\n+share/afterstep/start/Decorations/Cursors/plus\n+share/afterstep/start/Decorations/Cursors/question_arrow\n+share/afterstep/start/Decorations/Cursors/right_ptr\n+share/afterstep/start/Decorations/Cursors/right_side\n+share/afterstep/start/Decorations/Cursors/right_tee\n+share/afterstep/start/Decorations/Cursors/shuttle\n+share/afterstep/start/Decorations/Cursors/rightbutton\n+share/afterstep/start/Decorations/Cursors/rtl_logo\n+share/afterstep/start/Decorations/Cursors/sailboat\n+share/afterstep/start/Decorations/Cursors/sb_down_arrow\n+share/afterstep/start/Decorations/Cursors/sb_h_double_arrow\n+share/afterstep/start/Decorations/Cursors/sb_left_arrow\n+share/afterstep/start/Decorations/Cursors/sb_right_arrow\n+share/afterstep/start/Decorations/Cursors/sb_up_arrow\n+share/afterstep/start/Decorations/Cursors/sb_v_double_arrow\n+share/afterstep/start/Decorations/Cursors/spider\n+share/afterstep/start/Decorations/Cursors/sizing\n+share/afterstep/start/Decorations/Cursors/spraycan\n+share/afterstep/start/Decorations/Cursors/star\n+share/afterstep/start/Decorations/Cursors/target\n+share/afterstep/start/Decorations/Cursors/tcross\n+share/afterstep/start/Decorations/Cursors/top_left_arrow\n+share/afterstep/start/Decorations/Cursors/top_left_corner\n+share/afterstep/start/Decorations/Cursors/top_right_corner\n+share/afterstep/start/Decorations/Cursors/top_side\n+share/afterstep/start/Decorations/Cursors/top_tee\n+share/afterstep/start/Decorations/Cursors/trek\n+share/afterstep/start/Decorations/Cursors/ul_angle\n+share/afterstep/start/Decorations/Cursors/umbrella\n+share/afterstep/start/Decorations/Cursors/ur_angle\n+share/afterstep/start/Decorations/Cursors/watch\n+share/afterstep/start/Decorations/Cursors/X_cursor\n+share/afterstep/start/Decorations/Mouse/Left Handed (3 2 1)\n+share/afterstep/start/Decorations/Mouse/Ultra Fastest\n+share/afterstep/start/Decorations/Mouse/Faster\n+share/afterstep/start/Decorations/Mouse/Fast\n+share/afterstep/start/Decorations/Mouse/Normal\n+share/afterstep/start/Decorations/Mouse/Slower\n+share/afterstep/start/Decorations/Mouse/No acceleration\n+share/afterstep/start/Decorations/Mouse/Right Handed (1 2 3)\n+share/afterstep/start/Decorations/Mouse/Next Fastest\n+share/afterstep/start/Decorations/X earth\n+share/afterstep/start/Decorations/Stop animation\n+share/afterstep/start/Decorations/X fishtank\n+share/afterstep/start/AfterStepDoc\n+share/afterstep/start/Help about ...\n+share/afterstep/start/Find a file ...\n+share/afterstep/start/X terminal (big)\n+share/afterstep/start/Run a command ...\n+share/afterstep/start/X terminal (pixmap)\n+share/afterstep/start/Screen saver\n+share/afterstep/start/X terminal\n+share/afterstep/start/X terminal (no sb)\n+share/afterstep/feels/feel.Windowish\n+share/afterstep/feels/feel.ICCCM\n+share/afterstep/feels/feel.AutoRaise\n+share/afterstep/feels/feel.ClickToFocus\n+share/afterstep/feels/feel.PureNeXT\n+share/afterstep/feels/feel.DEFAULT\n+share/afterstep/desktop/backgrounds/wheat.xpm\n+share/afterstep/desktop/backgrounds/Wave.xpm\n+share/afterstep/desktop/backgrounds/red.xpm\n+share/afterstep/desktop/backgrounds/midnightblue.xpm\n+share/afterstep/desktop/backgrounds/darkgreen.xpm\n+share/afterstep/desktop/backgrounds/black.xpm\n+share/afterstep/desktop/backgrounds/aquamarine.xpm\n+share/afterstep/desktop/backgrounds/darkblue.xpm\n+share/afterstep/desktop/backgrounds/purple.xpm\n+share/afterstep/desktop/backgrounds/Back.xpm\n+share/afterstep/desktop/icons/8bpp/ASBBlockConvexBlue.xpm\n+share/afterstep/desktop/icons/8bpp/ASBBlockGreen.xpm\n+share/afterstep/desktop/icons/8bpp/ASBBlockMarble.xpm\n+share/afterstep/desktop/icons/8bpp/ASBBlockRed.xpm\n+share/afterstep/desktop/icons/8bpp/ASBBlockSlate.xpm\n+share/afterstep/desktop/icons/8bpp/ASBBlockWater.xpm\n+share/afterstep/desktop/icons/8bpp/3dpaint.xpm\n+share/afterstep/desktop/icons/8bpp/Eyecon.xpm\n+share/afterstep/desktop/icons/8bpp/Paint.xpm\n+share/afterstep/desktop/icons/8bpp/Plasma.xpm\n+share/afterstep/desktop/icons/8bpp/ShutDown.xpm\n+share/afterstep/desktop/icons/8bpp/Folder.xpm\n+share/afterstep/desktop/icons/8bpp/interface.xpm\n+share/afterstep/desktop/icons/8bpp/linux-penguin.xpm\n+share/afterstep/desktop/icons/8bpp/monalisa.xpm\n+share/afterstep/desktop/icons/8bpp/netscape.xpm\n+share/afterstep/desktop/icons/8bpp/wharf.xpm\n+share/afterstep/desktop/icons/8bpp/writeletter.xpm\n+share/afterstep/desktop/icons/8bpp/FileFolders.xpm\n+share/afterstep/desktop/icons/8bpp/ASBBlockWhite.xpm\n+share/afterstep/desktop/icons/8bpp/Text.xpm\n+share/afterstep/desktop/icons/8bpp/Monitor.xpm\n+share/afterstep/desktop/icons/8bpp/shutdown.xpm\n+share/afterstep/desktop/icons/8bpp/CDrom.xpm\n+share/afterstep/desktop/icons/8bpp/Recycler.xpm\n+share/afterstep/desktop/icons/8bpp/ASBBlockDefault.xpm\n+share/afterstep/desktop/icons/8bpp/ASBBlockClear.xpm\n+share/afterstep/desktop/icons/8bpp/OldFashionedRadio.xpm\n+share/afterstep/desktop/icons/8bpp/YellowBlueRedGeometry.xpm\n+share/afterstep/desktop/icons/8bpp/AfterStep2.xpm\n+share/afterstep/desktop/icons/8bpp/KeysOnChain.xpm\n+share/afterstep/desktop/icons/8bpp/AfterStep.xpm\n+share/afterstep/desktop/icons/8bpp/AfterStep4.xpm\n+share/afterstep/desktop/icons/8bpp/ComputerPC.xpm\n+share/afterstep/desktop/icons/8bpp/Bookshelf.xpm\n+share/afterstep/desktop/icons/8bpp/Brush.xpm\n+share/afterstep/desktop/icons/8bpp/CDrom2.xpm\n+share/afterstep/desktop/icons/8bpp/Computer.xpm\n+share/afterstep/desktop/icons/8bpp/Publish.xpm\n+share/afterstep/desktop/icons/8bpp/WWW.xpm\n+share/afterstep/desktop/icons/8bpp/cpuchip.xpm\n+share/afterstep/desktop/icons/8bpp/Database.xpm\n+share/afterstep/desktop/icons/8bpp/Debug.xpm\n+share/afterstep/desktop/icons/8bpp/DeskGlobe.xpm\n+share/afterstep/desktop/icons/8bpp/disk.builder.xpm\n+share/afterstep/desktop/icons/8bpp/draw.xpm\n+share/afterstep/desktop/icons/8bpp/hostmanager.xpm\n+share/afterstep/desktop/icons/8bpp/Install.xpm\n+share/afterstep/desktop/icons/8bpp/KeyPower.xpm\n+share/afterstep/desktop/icons/8bpp/RayTracedGear.xpm\n+share/afterstep/desktop/icons/8bpp/Start.xpm\n+share/afterstep/desktop/icons/8bpp/Network.xpm\n+share/afterstep/desktop/icons/8bpp/workshop.xpm\n+share/afterstep/desktop/icons/8bpp/widget.xpm\n+share/afterstep/desktop/icons/8bpp/spreadsheet.xpm\n+share/afterstep/desktop/icons/8bpp/spreadsheet2.xpm\n+share/afterstep/desktop/icons/8bpp/e-no.xpm\n+share/afterstep/desktop/icons/8bpp/e0.xpm\n+share/afterstep/desktop/icons/8bpp/BookArrows.xpm\n+share/afterstep/desktop/icons/8bpp/GNUSpace.xpm\n+share/afterstep/desktop/icons/8bpp/Info.xpm\n+share/afterstep/desktop/icons/8bpp/e1.xpm\n+share/afterstep/desktop/icons/8bpp/e10.xpm\n+share/afterstep/desktop/icons/8bpp/NetworkInfoManager.xpm\n+share/afterstep/desktop/icons/8bpp/e11.xpm\n+share/afterstep/desktop/icons/8bpp/e2.xpm\n+share/afterstep/desktop/icons/8bpp/e3.xpm\n+share/afterstep/desktop/icons/8bpp/e4.xpm\n+share/afterstep/desktop/icons/8bpp/e5.xpm\n+share/afterstep/desktop/icons/8bpp/e6.xpm\n+share/afterstep/desktop/icons/8bpp/e7.xpm\n+share/afterstep/desktop/icons/8bpp/author.xpm\n+share/afterstep/desktop/icons/8bpp/AfterStep3.xpm\n+share/afterstep/desktop/icons/8bpp/e8.xpm\n+share/afterstep/desktop/icons/8bpp/e9.xpm\n+share/afterstep/desktop/icons/8bpp/AfterStep5.xpm\n+share/afterstep/desktop/icons/8bpp/RedFire.xpm\n+share/afterstep/desktop/icons/8bpp/ASBBlockBlue.xpm\n+share/afterstep/desktop/icons/common/fr.xpm\n+share/afterstep/desktop/icons/common/xiterm.xpm\n+share/afterstep/desktop/icons/common/Earth.xpm\n+share/afterstep/desktop/icons/common/arrow.xpm\n+share/afterstep/desktop/icons/common/World.xpm\n+share/afterstep/desktop/icons/common/monitor-e0.xpm\n+share/afterstep/desktop/icons/common/monitor-e1.xpm\n+share/afterstep/desktop/icons/common/monitor-e10.xpm\n+share/afterstep/desktop/icons/common/monitor-e11.xpm\n+share/afterstep/desktop/icons/common/monitor-e2.xpm\n+share/afterstep/desktop/icons/common/monitor-e3.xpm\n+share/afterstep/desktop/icons/common/monitor-e4.xpm\n+share/afterstep/desktop/icons/common/monitor-e5.xpm\n+share/afterstep/desktop/icons/common/monitor-e6.xpm\n+share/afterstep/desktop/icons/common/monitor-e7.xpm\n+share/afterstep/desktop/icons/common/monitor-e8.xpm\n+share/afterstep/desktop/icons/common/monitor-e9.xpm\n+share/afterstep/desktop/icons/common/monitor-no.xpm\n+share/afterstep/desktop/icons/common/Mail1.xpm\n+share/afterstep/desktop/icons/common/Mail2.xpm\n+share/afterstep/desktop/icons/common/Mail3.xpm\n+share/afterstep/desktop/icons/common/98.xpm\n+share/afterstep/desktop/icons/common/AfterStep7.xpm\n+share/afterstep/desktop/icons/common/AfterStep8.xpm\n+share/afterstep/desktop/icons/common/dk.xpm\n+share/afterstep/desktop/icons/16bpp/ASBBlockClear.xpm\n+share/afterstep/desktop/icons/16bpp/ASBBlockConvexBlue.xpm\n+share/afterstep/desktop/icons/16bpp/ASBBlockDefault.xpm\n+share/afterstep/desktop/icons/16bpp/ASBBlockGreen.xpm\n+share/afterstep/desktop/icons/16bpp/ASBBlockMarble.xpm\n+share/afterstep/desktop/icons/16bpp/ASBBlockRed.xpm\n+share/afterstep/desktop/icons/16bpp/ASBBlockSlate.xpm\n+share/afterstep/desktop/icons/16bpp/ASBBlockWater.xpm\n+share/afterstep/desktop/icons/16bpp/ASBBlockWhite.xpm\n+share/afterstep/desktop/icons/16bpp/CDrom.xpm\n+share/afterstep/desktop/icons/16bpp/Eyecon.xpm\n+share/afterstep/desktop/icons/16bpp/Folder.xpm\n+share/afterstep/desktop/icons/16bpp/KeysOnChain.xpm\n+share/afterstep/desktop/icons/16bpp/Monitor.xpm\n+share/afterstep/desktop/icons/16bpp/Paint.xpm\n+share/afterstep/desktop/icons/16bpp/Plasma.xpm\n+share/afterstep/desktop/icons/16bpp/Recycler.xpm\n+share/afterstep/desktop/icons/16bpp/ShutDown.xpm\n+share/afterstep/desktop/icons/16bpp/WWW.xpm\n+share/afterstep/desktop/icons/16bpp/Text.xpm\n+share/afterstep/desktop/icons/16bpp/interface.xpm\n+share/afterstep/desktop/icons/16bpp/linux-penguin.xpm\n+share/afterstep/desktop/icons/16bpp/monalisa.xpm\n+share/afterstep/desktop/icons/16bpp/netscape.xpm\n+share/afterstep/desktop/icons/16bpp/wharf.xpm\n+share/afterstep/desktop/icons/16bpp/writeletter.xpm\n+share/afterstep/desktop/icons/16bpp/3dpaint.xpm\n+share/afterstep/desktop/icons/16bpp/OldFashionedRadio.xpm\n+share/afterstep/desktop/icons/16bpp/YellowBlueRedGeometry.xpm\n+share/afterstep/desktop/icons/16bpp/AfterStep2.xpm\n+share/afterstep/desktop/icons/16bpp/shutdown.xpm\n+share/afterstep/desktop/icons/16bpp/FileFolders.xpm\n+share/afterstep/desktop/icons/16bpp/AfterStep.xpm\n+share/afterstep/desktop/icons/16bpp/AfterStep3.xpm\n+share/afterstep/desktop/icons/16bpp/AfterStep4.xpm\n+share/afterstep/desktop/icons/16bpp/BookArrows.xpm\n+share/afterstep/desktop/icons/16bpp/Bookshelf.xpm\n+share/afterstep/desktop/icons/16bpp/Brush.xpm\n+share/afterstep/desktop/icons/16bpp/CDrom2.xpm\n+share/afterstep/desktop/icons/16bpp/Computer.xpm\n+share/afterstep/desktop/icons/16bpp/Info.xpm\n+share/afterstep/desktop/icons/16bpp/ComputerPC.xpm\n+share/afterstep/desktop/icons/16bpp/Database.xpm\n+share/afterstep/desktop/icons/16bpp/Debug.xpm\n+share/afterstep/desktop/icons/16bpp/DeskGlobe.xpm\n+share/afterstep/desktop/icons/16bpp/GNUSpace.xpm\n+share/afterstep/desktop/icons/16bpp/Install.xpm\n+share/afterstep/desktop/icons/16bpp/KeyPower.xpm\n+share/afterstep/desktop/icons/16bpp/Network.xpm\n+share/afterstep/desktop/icons/16bpp/NetworkInfoManager.xpm\n+share/afterstep/desktop/icons/16bpp/e-no.xpm\n+share/afterstep/desktop/icons/16bpp/Publish.xpm\n+share/afterstep/desktop/icons/16bpp/RayTracedGear.xpm\n+share/afterstep/desktop/icons/16bpp/author.xpm\n+share/afterstep/desktop/icons/16bpp/cpuchip.xpm\n+share/afterstep/desktop/icons/16bpp/disk.builder.xpm\n+share/afterstep/desktop/icons/16bpp/draw.xpm\n+share/afterstep/desktop/icons/16bpp/hostmanager.xpm\n+share/afterstep/desktop/icons/16bpp/e0.xpm\n+share/afterstep/desktop/icons/16bpp/spreadsheet.xpm\n+share/afterstep/desktop/icons/16bpp/spreadsheet2.xpm\n+share/afterstep/desktop/icons/16bpp/e1.xpm\n+share/afterstep/desktop/icons/16bpp/e10.xpm\n+share/afterstep/desktop/icons/16bpp/widget.xpm\n+share/afterstep/desktop/icons/16bpp/workshop.xpm\n+share/afterstep/desktop/icons/16bpp/Start.xpm\n+share/afterstep/desktop/icons/16bpp/e11.xpm\n+share/afterstep/desktop/icons/16bpp/e2.xpm\n+share/afterstep/desktop/icons/16bpp/e3.xpm\n+share/afterstep/desktop/icons/16bpp/e4.xpm\n+share/afterstep/desktop/icons/16bpp/e5.xpm\n+share/afterstep/desktop/icons/16bpp/e6.xpm\n+share/afterstep/desktop/icons/16bpp/e7.xpm\n+share/afterstep/desktop/icons/16bpp/e8.xpm\n+share/afterstep/desktop/icons/16bpp/e9.xpm\n+share/afterstep/desktop/icons/16bpp/AfterStep5.xpm\n+share/afterstep/desktop/icons/16bpp/RedFire.xpm\n+share/afterstep/desktop/icons/16bpp/ASBBlockBlue.xpm\n+share/afterstep/desktop/buttons/1p-e.xpm\n+share/afterstep/desktop/buttons/1.xpm\n+share/afterstep/desktop/buttons/as-iconize-pressed.xpm\n+share/afterstep/desktop/buttons/as-iconize.xpm\n+share/afterstep/desktop/buttons/as-kill-pressed.xpm\n+share/afterstep/desktop/buttons/as-kill.xpm\n+share/afterstep/desktop/buttons/as-maximize-a-pressed.xpm\n+share/afterstep/desktop/buttons/as-maximize-a.xpm\n+share/afterstep/desktop/buttons/as-menu-a-pressed.xpm\n+share/afterstep/desktop/buttons/as-menu-a.xpm\n+share/afterstep/desktop/buttons/as-menu-b-pressed.xpm\n+share/afterstep/desktop/buttons/as-menu-b.xpm\n+share/afterstep/desktop/buttons/as-minimize-a-pressed.xpm\n+share/afterstep/desktop/buttons/as-minimize-a.xpm\n+share/afterstep/desktop/buttons/as-shade-a-pressed.xpm\n+share/afterstep/desktop/buttons/as-shade-a.xpm\n+share/afterstep/desktop/buttons/1p.xpm\n+share/afterstep/desktop/buttons/as-switchwindow-a.xpm\n+share/afterstep/desktop/buttons/as-switchwindow-a-pressed.xpm\n+share/afterstep/desktop/buttons/as-switchwindow-b-pressed.xpm\n+share/afterstep/desktop/buttons/as-switchwindow-b.xpm\n+share/afterstep/desktop/buttons/as-switchwindow-c-pressed.xpm\n+share/afterstep/desktop/buttons/as-switchwindow-c.xpm\n+share/afterstep/desktop/buttons/2.xpm\n+share/afterstep/desktop/buttons/2p.xpm\n+share/afterstep/desktop/buttons/3.xpm\n+share/afterstep/desktop/buttons/3p.xpm\n+share/afterstep/desktop/buttons/4.xpm\n+share/afterstep/desktop/buttons/4p.xpm\n+share/afterstep/desktop/buttons/5.xpm\n+share/afterstep/desktop/buttons/5p.xpm\n+share/afterstep/desktop/buttons/2-e.xpm\n+share/afterstep/desktop/buttons/2p-e.xpm\n+share/afterstep/desktop/buttons/3-e.xpm\n+share/afterstep/desktop/buttons/3p-e.xpm\n+share/afterstep/desktop/buttons/4-e.xpm\n+share/afterstep/desktop/buttons/4p-e.xpm\n+share/afterstep/desktop/buttons/5-e.xpm\n+share/afterstep/desktop/buttons/5p-e.xpm\n+share/afterstep/desktop/buttons/1-e.xpm\n+share/afterstep/desktop/sounds/train.au\n+share/afterstep/desktop/sounds/clink.au\n+share/afterstep/desktop/sounds/cowbell.au\n+share/afterstep/desktop/sounds/crash.au\n+share/afterstep/desktop/sounds/drip.au\n+share/afterstep/desktop/sounds/gong.au\n+share/afterstep/desktop/sounds/meepmeep.au\n+share/afterstep/desktop/sounds/bong.au\n+share/afterstep/audio\n+share/afterstep/autoexec\n+share/afterstep/base.16bpp\n+share/afterstep/base.24bpp\n+share/afterstep/base.8bpp\n+share/afterstep/clean\n+share/afterstep/database\n+share/afterstep/forms\n+share/afterstep/ident\n+share/afterstep/pager\n+share/afterstep/scroll\n+share/afterstep/wharf\n+share/afterstep/winlist\n+share/afterstep/compatibility\n+share/afterstep/zharf\n+share/afterstep/.workspace_state\n+share/afterstep/animate\n+share/afterstep/asmail\n+share/doc/afterstep/afterstep.html\n+share/doc/afterstep/afterstep-1.html\n+share/doc/afterstep/afterstep-2.html\n+share/doc/afterstep/afterstep-3.html\n+share/doc/afterstep/afterstep-4.html\n+share/doc/afterstep/afterstep-5.html\n+share/doc/afterstep/afterstep-6.html\n+share/doc/afterstep/afterstep-7.html\n+share/doc/afterstep/afterstep-8.html\n+share/doc/afterstep/afterstep-9.html\n+@dirrm share/afterstep/looks\n+@dirrm share/afterstep/non-configurable/desk1\n+@dirrm share/afterstep/non-configurable/desk0\n+@dirrm share/afterstep/non-configurable/desk2\n+@dirrm share/afterstep/non-configurable/desk3\n+@dirrm share/afterstep/non-configurable/tmp\n+@dirrm share/afterstep/non-configurable\n+@dirrm share/afterstep/start/Quit\n+@dirrm share/afterstep/start/Modules\n+@dirrm share/afterstep/start/Screen savers/Without password\n+@dirrm share/afterstep/start/Screen savers/With password\n+@dirrm share/afterstep/start/Screen savers\n+@dirrm share/afterstep/start/Applications/Office\n+@dirrm share/afterstep/start/Applications/Games\n+@dirrm share/afterstep/start/Applications/KDE/KDE-Games\n+@dirrm share/afterstep/start/Applications/KDE\n+@dirrm share/afterstep/start/Applications/Accessories\n+@dirrm share/afterstep/start/Applications/StEP applications\n+@dirrm share/afterstep/start/Applications/Network\n+@dirrm share/afterstep/start/Applications/Medias\n+@dirrm share/afterstep/start/Applications\n+@dirrm share/afterstep/start/Decorations/Animations\n+@dirrm share/afterstep/start/Decorations/Cursors\n+@dirrm share/afterstep/start/Decorations/Mouse\n+@dirrm share/afterstep/start/Decorations\n+@dirrm share/afterstep/start\n+@dirrm share/afterstep/feels\n+@dirrm share/afterstep/desktop/backgrounds\n+@dirrm share/afterstep/desktop/icons/8bpp\n+@dirrm share/afterstep/desktop/icons/common\n+@dirrm share/afterstep/desktop/icons/16bpp\n+@dirrm share/afterstep/desktop/icons\n+@dirrm share/afterstep/desktop/buttons\n+@dirrm share/afterstep/desktop/sounds\n+@dirrm share/afterstep/desktop\n+@dirrm share/doc/afterstep\n+@dirrm share/afterstep\ndiff -ruN afterstep144/scripts/configure afterstep-devel/scripts/configure\n--- afterstep144/scripts/configure\tTue Oct 29 12:50:21 1996\n+++ afterstep-devel/scripts/configure\tWed Dec 31 17:00:00 1969\n@@ -1,8 +0,0 @@\n-#!/usr/bin/perl\n-#\n-\n-eval '(exit $?0)' \u0026\u0026 eval 'exec /usr/bin/perl -S $0 ${1+\"$@\"}'\n-\u0026 eval 'exec /usr/bin/perl -S $0 $argv:q'\n-if 0;\n-\n-system( \"/usr/bin/perl -pi -e 's|%%PREFIX%%|$ENV{'PREFIX'}|g' $ENV{'WRKSRC'}/sample.steprc $ENV{'WRKSRC'}/configure.h\" );"
}