{
 "id": 1053875,
 "bug_id": 238413,
 "attachment_id": 0,
 "creation_time": "2019-06-10T20:32:11Z",
 "creator": "rfg-freebsd@tristatelogic.com",
 "text": "% uname -a\nFreeBSD coredump.tristatelogic.com 12.0-RELEASE FreeBSD 12.0-RELEASE r341666 GENERIC  amd64\n\n% make showconfig -C /usr/ports/www/opera\n===\u003e The following configuration options are available for opera-12.16_6:\n     CUPS=on: support for printing (requires CUPS)\n     VIDEO=on: support for HTML5 video (requires GStreamer)\n     GTK2=off: GTK+ 2 GUI toolkit support\n     KDE4=off: KDE 4 desktop environment support\n===\u003e Use 'make config' to modify these settings\n\nPLEASE NOTE:  I *did not* build this from ports.  I installed the opera pre-built package."
}