{
 "id": 475281,
 "bug_id": 129727,
 "attachment_id": 0,
 "creation_time": "2008-12-19T04:50:45Z",
 "creator": "linimon@lonesome.com",
 "text": "----- Forwarded message from Helmut Schneider \u003cjumper99@gmx.de\u003e -----\n\nFrom: Helmut Schneider \u003cjumper99@gmx.de\u003e\nSubject: Re: ports/129727: www/tomcat6 port fails to reinstall in some cases\n\nedwin@FreeBSD.org \u003cedwin@FreeBSD.org\u003e wrote:\n\u003eOver to maintainer (via the GNATS Auto Assign Tool)\n\u003e\n\u003ehttp://www.freebsd.org/cgi/query-pr.cgi?pr=129727\n\nSee http://www.freebsd.org/cgi/query-pr.cgi?pr=129666\n\n----- End forwarded message -----"
}