{
  "actual_time": "",
  "alias": [],
  "assigned_to": "np@FreeBSD.org",
  "assigned_to_detail": {
    "id": 25030,
    "email": "np@FreeBSD.org",
    "name": "np@FreeBSD.org",
    "can_login": false,
    "real_name": "Navdeep Parhar",
    "groups": null
  },
  "blocks": [],
  "cc": [],
  "cc_detail": [],
  "classification": "Unclassified",
  "component": "kern",
  "creation_time": "2011-12-22T20:00:26Z",
  "creator": "dan.mcgregor@usask.ca",
  "creator_detail": {
    "id": 29579,
    "email": "dan.mcgregor@usask.ca",
    "name": "dan.mcgregor@usask.ca",
    "can_login": false,
    "real_name": "Dan McGregor",
    "groups": null
  },
  "deadline": "",
  "depends_on": [],
  "dupe_of": 0,
  "estimated_time": "",
  "flags": [],
  "groups": [],
  "id": 163545,
  "is_cc_accessible": true,
  "is_confirmed": true,
  "is_open": false,
  "is_creator_accessible": true,
  "keywords": [],
  "last_change_time": "2012-10-25T20:11:06Z",
  "op_sys": "Any",
  "platform": "Any",
  "priority": "Normal",
  "product": "Base System",
  "qa_contact": "",
  "qa_contact_detail": {
    "id": 0,
    "email": "",
    "name": "",
    "can_login": false,
    "real_name": "",
    "groups": null
  },
  "remaining_time": "",
  "resolution": "FIXED",
  "see_also": [],
  "severity": "Affects Only Me",
  "status": "Closed",
  "summary": "[cxgb] [patch] Return of uninitialized value in Chelsio T3 driver",
  "target_milestone": "---",
  "update_token": "",
  "url": "",
  "version": "9.0-PRERELEASE",
  "whiteboard": ""
}