{
 "id": 1031030,
 "bug_id": 234771,
 "attachment_id": 0,
 "creation_time": "2019-01-09T20:43:43Z",
 "creator": "emaste@freebsd.org",
 "text": "(In reply to Kubilay Kocak from comment #4)\n\u003e   --currently-running release\n\u003e                -- Update as if currently running this release\n\nFurther issues - this command does not indicate the required format of the \"release\" string or validate the provided release, so the same opaque error is emitted if the user specifies e.g. \"11.2\" instead of \"11.2-RELEASE\"."
}