{
 "id": 6683,
 "bug_id": 2209,
 "attachment_id": 0,
 "creation_time": "1996-12-14T07:10:01Z",
 "creator": "sanpei@yy.cs.keio.ac.jp",
 "text": "\n  I updated jp-mh(ports/japanese/mh), and put ports files:\n\n\tftp://ftp.FreeBSD.ORG/pub/FreeBSD/incoming/jp-mh-96121401.tar.gz\n\n  Changes:\n\t*support POP protocols*\n\n\tpatch-aa\n\t\tsupport POP protocols (RPOP)\n\n\tpatch-ab\n\t\tspeed-up folder command patch from mew\n\n\tpatch-ac\n\t\timport from mail/mh/patches/patch-ac\n\n\tpatch-ag\n\t\tsmail (X-au..) error patch from mew\n\n\tpatch-ah\n\t\tfor MPOP,BPOP\n\n\n  Please submit these changes.\n\nThank you."
}