{
 "id": 874407,
 "bug_id": 206998,
 "attachment_id": 0,
 "creation_time": "2016-04-12T19:45:40Z",
 "creator": "rootservice@gmail.com",
 "text": "OK, then i'll prepare a series of as small as possible patches (issue by issue) starting with the plain update to 5.7.12 and then REVbumping for each issue.\n\nBTW: When i'm at it, should i also unbundle zlib ultimately by reverting https://bugs.freebsd.org/bugzilla/show_bug.cgi?id=198812 and setting -DWITH_ZLIB to system as we do with the other libs?"
}