{
 "id": 891932,
 "bug_id": 211691,
 "attachment_id": 0,
 "creation_time": "2016-08-09T12:24:02Z",
 "creator": "commit-hook@FreeBSD.org",
 "text": "A commit references this bug:\n\nAuthor: mat\nDate: Tue Aug  9 12:23:15 UTC 2016\nNew revision: 419917\nURL: https://svnweb.freebsd.org/changeset/ports/419917\n\nLog:\n  Add the correct version, the configure stage was saying:\n\n  Warning: prerequisite namespace::autoclean 0.19 not found.\n\n  PR:\t\t211691\n  Reported by:\tsfoster mailbox myzen co uk\n  Sponsored by:\tAbsolight\n\nChanges:\n  head/devel/p5-DateTime/Makefile"
}