{
 "id": 1081299,
 "bug_id": 242964,
 "attachment_id": 0,
 "creation_time": "2019-12-29T17:14:20Z",
 "creator": "bob@vesterman.com",
 "text": "/usr/ports/UPDATING has an entry on 20191216 for updating python to 3.7.  There's a specific section in there describing how to do it if you're using portmaster.  The instructions in that section do not work when using the default root shell.  Specifically, the line...\n\n# REINSTALL=\"$(pkg info -o py36-\\* | awk '{printf \"%s \", $2}')\"\n\n... fails with \"Illegal variable name.\"\n\nThe instructions work fine if you switch to bash, but perhaps they should be changed to work in the default shell.  At the very least, it should be noted in the UPDATING entry that the instructions require a specific non-default shell to be used."
}