{
 "id": 815060,
 "bug_id": 198588,
 "attachment_id": 0,
 "creation_time": "2015-03-15T01:24:16Z",
 "creator": "mij@sshguard.net",
 "text": "Hello folks,\n\nThanks for maintaining PostgreSQL so efficiently on FreeBSD!\n\nThe port's default config is to have \"XML\" enabled by default. This adds a dependency to libxml2, one of the ports with the worst security history [1]. This has 3 consequences:\n\n* bigger maintenance burden -- rebuilding the DBMS upon any libxml2 vulnerability, i.e. multiple/many times per year\n* lower uptime -- restarting the DBMS for every rebuild\n* lower security in default installation -- postgresql insecure when libxml2 is\n\nThe vanilla distribution of PostgreSQL has this disabled by default itself.\n\nI open for discussion if this default build option is worth maintaining. Do the majority of users make use of it? If not, I suggest making if off.\n\ncheers\nmichele\n\n[1] https://web.nvd.nist.gov/view/vuln/search-results?query=libxml2\u0026search_type=last3years\u0026cves=on"
}